{
  "url": "https://api.github.com/repos/NayamAmarshe/DeskCut/releases/59547718",
  "assets_url": "https://api.github.com/repos/NayamAmarshe/DeskCut/releases/59547718/assets",
  "upload_url": "https://uploads.github.com/repos/NayamAmarshe/DeskCut/releases/59547718/assets{?name,label}",
  "html_url": "https://github.com/NayamAmarshe/DeskCut/releases/tag/stable-1.5.0",
  "id": 59547718,
  "author": {
    "login": "NayamAmarshe",
    "id": 25067102,
    "node_id": "MDQ6VXNlcjI1MDY3MTAy",
    "avatar_url": "https://avatars.githubusercontent.com/u/25067102?v=4",
    "gravatar_id": "",
    "url": "https://api.github.com/users/NayamAmarshe",
    "html_url": "https://github.com/NayamAmarshe",
    "followers_url": "https://api.github.com/users/NayamAmarshe/followers",
    "following_url": "https://api.github.com/users/NayamAmarshe/following{/other_user}",
    "gists_url": "https://api.github.com/users/NayamAmarshe/gists{/gist_id}",
    "starred_url": "https://api.github.com/users/NayamAmarshe/starred{/owner}{/repo}",
    "subscriptions_url": "https://api.github.com/users/NayamAmarshe/subscriptions",
    "organizations_url": "https://api.github.com/users/NayamAmarshe/orgs",
    "repos_url": "https://api.github.com/users/NayamAmarshe/repos",
    "events_url": "https://api.github.com/users/NayamAmarshe/events{/privacy}",
    "received_events_url": "https://api.github.com/users/NayamAmarshe/received_events",
    "type": "User",
    "site_admin": false
  },
  "node_id": "RE_kwDOGyXZqc4DjKBG",
  "tag_name": "stable-1.5.0",
  "target_commitish": "main",
  "name": "DeskCut v1.5.0",
  "draft": false,
  "prerelease": false,
  "created_at": "2022-02-14T20:28:46Z",
  "published_at": "2022-02-14T20:35:06Z",
  "assets": [
    {
      "url": "https://api.github.com/repos/NayamAmarshe/DeskCut/releases/assets/56823637",
      "id": 56823637,
      "node_id": "RA_kwDOGyXZqc4DYw9V",
      "name": "DeskCut-1.5.0.AppImage",
      "label": null,
      "uploader": {
        "login": "NayamAmarshe",
        "id": 25067102,
        "node_id": "MDQ6VXNlcjI1MDY3MTAy",
        "avatar_url": "https://avatars.githubusercontent.com/u/25067102?v=4",
        "gravatar_id": "",
        "url": "https://api.github.com/users/NayamAmarshe",
        "html_url": "https://github.com/NayamAmarshe",
        "followers_url": "https://api.github.com/users/NayamAmarshe/followers",
        "following_url": "https://api.github.com/users/NayamAmarshe/following{/other_user}",
        "gists_url": "https://api.github.com/users/NayamAmarshe/gists{/gist_id}",
        "starred_url": "https://api.github.com/users/NayamAmarshe/starred{/owner}{/repo}",
        "subscriptions_url": "https://api.github.com/users/NayamAmarshe/subscriptions",
        "organizations_url": "https://api.github.com/users/NayamAmarshe/orgs",
        "repos_url": "https://api.github.com/users/NayamAmarshe/repos",
        "events_url": "https://api.github.com/users/NayamAmarshe/events{/privacy}",
        "received_events_url": "https://api.github.com/users/NayamAmarshe/received_events",
        "type": "User",
        "site_admin": false
      },
      "content_type": "application/vnd.appimage",
      "state": "uploaded",
      "size": 80961603,
      "download_count": 159,
      "created_at": "2022-02-14T20:31:48Z",
      "updated_at": "2022-02-14T20:31:59Z",
      "browser_download_url": "https://github.com/NayamAmarshe/DeskCut/releases/download/stable-1.5.0/DeskCut-1.5.0.AppImage"
    },
    {
      "url": "https://api.github.com/repos/NayamAmarshe/DeskCut/releases/assets/56827537",
      "id": 56827537,
      "node_id": "RA_kwDOGyXZqc4DYx6R",
      "name": "deskcut-1.5.0.x86_64.rpm",
      "label": null,
      "uploader": {
        "login": "NayamAmarshe",
        "id": 25067102,
        "node_id": "MDQ6VXNlcjI1MDY3MTAy",
        "avatar_url": "https://avatars.githubusercontent.com/u/25067102?v=4",
        "gravatar_id": "",
        "url": "https://api.github.com/users/NayamAmarshe",
        "html_url": "https://github.com/NayamAmarshe",
        "followers_url": "https://api.github.com/users/NayamAmarshe/followers",
        "following_url": "https://api.github.com/users/NayamAmarshe/following{/other_user}",
        "gists_url": "https://api.github.com/users/NayamAmarshe/gists{/gist_id}",
        "starred_url": "https://api.github.com/users/NayamAmarshe/starred{/owner}{/repo}",
        "subscriptions_url": "https://api.github.com/users/NayamAmarshe/subscriptions",
        "organizations_url": "https://api.github.com/users/NayamAmarshe/orgs",
        "repos_url": "https://api.github.com/users/NayamAmarshe/repos",
        "events_url": "https://api.github.com/users/NayamAmarshe/events{/privacy}",
        "received_events_url": "https://api.github.com/users/NayamAmarshe/received_events",
        "type": "User",
        "site_admin": false
      },
      "content_type": "application/x-rpm",
      "state": "uploaded",
      "size": 56677836,
      "download_count": 67,
      "created_at": "2022-02-14T20:53:48Z",
      "updated_at": "2022-02-14T20:53:59Z",
      "browser_download_url": "https://github.com/NayamAmarshe/DeskCut/releases/download/stable-1.5.0/deskcut-1.5.0.x86_64.rpm"
    },
    {
      "url": "https://api.github.com/repos/NayamAmarshe/DeskCut/releases/assets/56823627",
      "id": 56823627,
      "node_id": "RA_kwDOGyXZqc4DYw9L",
      "name": "deskcut_1.5.0_amd64.deb",
      "label": null,
      "uploader": {
        "login": "NayamAmarshe",
        "id": 25067102,
        "node_id": "MDQ6VXNlcjI1MDY3MTAy",
        "avatar_url": "https://avatars.githubusercontent.com/u/25067102?v=4",
        "gravatar_id": "",
        "url": "https://api.github.com/users/NayamAmarshe",
        "html_url": "https://github.com/NayamAmarshe",
        "followers_url": "https://api.github.com/users/NayamAmarshe/followers",
        "following_url": "https://api.github.com/users/NayamAmarshe/following{/other_user}",
        "gists_url": "https://api.github.com/users/NayamAmarshe/gists{/gist_id}",
        "starred_url": "https://api.github.com/users/NayamAmarshe/starred{/owner}{/repo}",
        "subscriptions_url": "https://api.github.com/users/NayamAmarshe/subscriptions",
        "organizations_url": "https://api.github.com/users/NayamAmarshe/orgs",
        "repos_url": "https://api.github.com/users/NayamAmarshe/repos",
        "events_url": "https://api.github.com/users/NayamAmarshe/events{/privacy}",
        "received_events_url": "https://api.github.com/users/NayamAmarshe/received_events",
        "type": "User",
        "site_admin": false
      },
      "content_type": "application/vnd.debian.binary-package",
      "state": "uploaded",
      "size": 56247686,
      "download_count": 279,
      "created_at": "2022-02-14T20:31:37Z",
      "updated_at": "2022-02-14T20:31:48Z",
      "browser_download_url": "https://github.com/NayamAmarshe/DeskCut/releases/download/stable-1.5.0/deskcut_1.5.0_amd64.deb"
    }
  ],
  "tarball_url": "https://api.github.com/repos/NayamAmarshe/DeskCut/tarball/stable-1.5.0",
  "zipball_url": "https://api.github.com/repos/NayamAmarshe/DeskCut/zipball/stable-1.5.0",
  "body": "Here's a new DeskCut release! 🚀 Here's what's new:\r\n\r\n✔ Dark Mode\r\n✔ RPM Package now available for Fedora users!   \r\n✔ Update Dialog to let you know when a new DeskCut version has released   \r\n✔ Fixed Placeholder mistakes   \r\n✔ Custom Exec Command Toggle changed   \r\n✔ Now you can enter custom icon paths!   \r\n\r\nHope DeskCut is proving to be helpful to you and I hope you like this release too 😄",
  "reactions": {
    "url": "https://api.github.com/repos/NayamAmarshe/DeskCut/releases/59547718/reactions",
    "total_count": 3,
    "+1": 0,
    "-1": 0,
    "laugh": 0,
    "hooray": 0,
    "confused": 0,
    "heart": 0,
    "rocket": 3,
    "eyes": 0
  }
}
