{
  "url": "https://api.github.com/repos/muesli/obs-cli/releases/58236917",
  "assets_url": "https://api.github.com/repos/muesli/obs-cli/releases/58236917/assets",
  "upload_url": "https://uploads.github.com/repos/muesli/obs-cli/releases/58236917/assets{?name,label}",
  "html_url": "https://github.com/muesli/obs-cli/releases/tag/v0.5.0",
  "id": 58236917,
  "author": {
    "login": "muesli",
    "id": 146378,
    "node_id": "MDQ6VXNlcjE0NjM3OA==",
    "avatar_url": "https://avatars.githubusercontent.com/u/146378?v=4",
    "gravatar_id": "",
    "url": "https://api.github.com/users/muesli",
    "html_url": "https://github.com/muesli",
    "followers_url": "https://api.github.com/users/muesli/followers",
    "following_url": "https://api.github.com/users/muesli/following{/other_user}",
    "gists_url": "https://api.github.com/users/muesli/gists{/gist_id}",
    "starred_url": "https://api.github.com/users/muesli/starred{/owner}{/repo}",
    "subscriptions_url": "https://api.github.com/users/muesli/subscriptions",
    "organizations_url": "https://api.github.com/users/muesli/orgs",
    "repos_url": "https://api.github.com/users/muesli/repos",
    "events_url": "https://api.github.com/users/muesli/events{/privacy}",
    "received_events_url": "https://api.github.com/users/muesli/received_events",
    "type": "User",
    "site_admin": false
  },
  "node_id": "RE_kwDODjSTC84DeJ_1",
  "tag_name": "v0.5.0",
  "target_commitish": "master",
  "name": "v0.5.0",
  "draft": false,
  "prerelease": false,
  "created_at": "2022-01-28T23:34:48Z",
  "published_at": "2022-01-28T23:43:06Z",
  "assets": [
    {
      "url": "https://api.github.com/repos/muesli/obs-cli/releases/assets/55248925",
      "id": 55248925,
      "node_id": "RA_kwDODjSTC84DSwgd",
      "name": "checksums.txt",
      "label": "",
      "uploader": {
        "login": "muesli",
        "id": 146378,
        "node_id": "MDQ6VXNlcjE0NjM3OA==",
        "avatar_url": "https://avatars.githubusercontent.com/u/146378?v=4",
        "gravatar_id": "",
        "url": "https://api.github.com/users/muesli",
        "html_url": "https://github.com/muesli",
        "followers_url": "https://api.github.com/users/muesli/followers",
        "following_url": "https://api.github.com/users/muesli/following{/other_user}",
        "gists_url": "https://api.github.com/users/muesli/gists{/gist_id}",
        "starred_url": "https://api.github.com/users/muesli/starred{/owner}{/repo}",
        "subscriptions_url": "https://api.github.com/users/muesli/subscriptions",
        "organizations_url": "https://api.github.com/users/muesli/orgs",
        "repos_url": "https://api.github.com/users/muesli/repos",
        "events_url": "https://api.github.com/users/muesli/events{/privacy}",
        "received_events_url": "https://api.github.com/users/muesli/received_events",
        "type": "User",
        "site_admin": false
      },
      "content_type": "text/plain; charset=utf-8",
      "state": "uploaded",
      "size": 3630,
      "download_count": 13,
      "created_at": "2022-01-28T23:43:20Z",
      "updated_at": "2022-01-28T23:43:20Z",
      "browser_download_url": "https://github.com/muesli/obs-cli/releases/download/v0.5.0/checksums.txt"
    },
    {
      "url": "https://api.github.com/repos/muesli/obs-cli/releases/assets/55248884",
      "id": 55248884,
      "node_id": "RA_kwDODjSTC84DSwf0",
      "name": "checksums.txt.sig",
      "label": "",
      "uploader": {
        "login": "muesli",
        "id": 146378,
        "node_id": "MDQ6VXNlcjE0NjM3OA==",
        "avatar_url": "https://avatars.githubusercontent.com/u/146378?v=4",
        "gravatar_id": "",
        "url": "https://api.github.com/users/muesli",
        "html_url": "https://github.com/muesli",
        "followers_url": "https://api.github.com/users/muesli/followers",
        "following_url": "https://api.github.com/users/muesli/following{/other_user}",
        "gists_url": "https://api.github.com/users/muesli/gists{/gist_id}",
        "starred_url": "https://api.github.com/users/muesli/starred{/owner}{/repo}",
        "subscriptions_url": "https://api.github.com/users/muesli/subscriptions",
        "organizations_url": "https://api.github.com/users/muesli/orgs",
        "repos_url": "https://api.github.com/users/muesli/repos",
        "events_url": "https://api.github.com/users/muesli/events{/privacy}",
        "received_events_url": "https://api.github.com/users/muesli/received_events",
        "type": "User",
        "site_admin": false
      },
      "content_type": "application/pgp-signature",
      "state": "uploaded",
      "size": 310,
      "download_count": 3,
      "created_at": "2022-01-28T23:43:07Z",
      "updated_at": "2022-01-28T23:43:07Z",
      "browser_download_url": "https://github.com/muesli/obs-cli/releases/download/v0.5.0/checksums.txt.sig"
    },
    {
      "url": "https://api.github.com/repos/muesli/obs-cli/releases/assets/55248896",
      "id": 55248896,
      "node_id": "RA_kwDODjSTC84DSwgA",
      "name": "obs-cli_0.5.0_Darwin_arm64.tar.gz",
      "label": "",
      "uploader": {
        "login": "muesli",
        "id": 146378,
        "node_id": "MDQ6VXNlcjE0NjM3OA==",
        "avatar_url": "https://avatars.githubusercontent.com/u/146378?v=4",
        "gravatar_id": "",
        "url": "https://api.github.com/users/muesli",
        "html_url": "https://github.com/muesli",
        "followers_url": "https://api.github.com/users/muesli/followers",
        "following_url": "https://api.github.com/users/muesli/following{/other_user}",
        "gists_url": "https://api.github.com/users/muesli/gists{/gist_id}",
        "starred_url": "https://api.github.com/users/muesli/starred{/owner}{/repo}",
        "subscriptions_url": "https://api.github.com/users/muesli/subscriptions",
        "organizations_url": "https://api.github.com/users/muesli/orgs",
        "repos_url": "https://api.github.com/users/muesli/repos",
        "events_url": "https://api.github.com/users/muesli/events{/privacy}",
        "received_events_url": "https://api.github.com/users/muesli/received_events",
        "type": "User",
        "site_admin": false
      },
      "content_type": "application/gzip",
      "state": "uploaded",
      "size": 2520609,
      "download_count": 28,
      "created_at": "2022-01-28T23:43:07Z",
      "updated_at": "2022-01-28T23:43:18Z",
      "browser_download_url": "https://github.com/muesli/obs-cli/releases/download/v0.5.0/obs-cli_0.5.0_Darwin_arm64.tar.gz"
    },
    {
      "url": "https://api.github.com/repos/muesli/obs-cli/releases/assets/55248904",
      "id": 55248904,
      "node_id": "RA_kwDODjSTC84DSwgI",
      "name": "obs-cli_0.5.0_Darwin_x86_64.tar.gz",
      "label": "",
      "uploader": {
        "login": "muesli",
        "id": 146378,
        "node_id": "MDQ6VXNlcjE0NjM3OA==",
        "avatar_url": "https://avatars.githubusercontent.com/u/146378?v=4",
        "gravatar_id": "",
        "url": "https://api.github.com/users/muesli",
        "html_url": "https://github.com/muesli",
        "followers_url": "https://api.github.com/users/muesli/followers",
        "following_url": "https://api.github.com/users/muesli/following{/other_user}",
        "gists_url": "https://api.github.com/users/muesli/gists{/gist_id}",
        "starred_url": "https://api.github.com/users/muesli/starred{/owner}{/repo}",
        "subscriptions_url": "https://api.github.com/users/muesli/subscriptions",
        "organizations_url": "https://api.github.com/users/muesli/orgs",
        "repos_url": "https://api.github.com/users/muesli/repos",
        "events_url": "https://api.github.com/users/muesli/events{/privacy}",
        "received_events_url": "https://api.github.com/users/muesli/received_events",
        "type": "User",
        "site_admin": false
      },
      "content_type": "application/gzip",
      "state": "uploaded",
      "size": 2558312,
      "download_count": 42,
      "created_at": "2022-01-28T23:43:08Z",
      "updated_at": "2022-01-28T23:43:18Z",
      "browser_download_url": "https://github.com/muesli/obs-cli/releases/download/v0.5.0/obs-cli_0.5.0_Darwin_x86_64.tar.gz"
    },
    {
      "url": "https://api.github.com/repos/muesli/obs-cli/releases/assets/55248883",
      "id": 55248883,
      "node_id": "RA_kwDODjSTC84DSwfz",
      "name": "obs-cli_0.5.0_freebsd_arm64.tar.gz",
      "label": "",
      "uploader": {
        "login": "muesli",
        "id": 146378,
        "node_id": "MDQ6VXNlcjE0NjM3OA==",
        "avatar_url": "https://avatars.githubusercontent.com/u/146378?v=4",
        "gravatar_id": "",
        "url": "https://api.github.com/users/muesli",
        "html_url": "https://github.com/muesli",
        "followers_url": "https://api.github.com/users/muesli/followers",
        "following_url": "https://api.github.com/users/muesli/following{/other_user}",
        "gists_url": "https://api.github.com/users/muesli/gists{/gist_id}",
        "starred_url": "https://api.github.com/users/muesli/starred{/owner}{/repo}",
        "subscriptions_url": "https://api.github.com/users/muesli/subscriptions",
        "organizations_url": "https://api.github.com/users/muesli/orgs",
        "repos_url": "https://api.github.com/users/muesli/repos",
        "events_url": "https://api.github.com/users/muesli/events{/privacy}",
        "received_events_url": "https://api.github.com/users/muesli/received_events",
        "type": "User",
        "site_admin": false
      },
      "content_type": "application/gzip",
      "state": "uploaded",
      "size": 2263837,
      "download_count": 3,
      "created_at": "2022-01-28T23:43:07Z",
      "updated_at": "2022-01-28T23:43:17Z",
      "browser_download_url": "https://github.com/muesli/obs-cli/releases/download/v0.5.0/obs-cli_0.5.0_freebsd_arm64.tar.gz"
    },
    {
      "url": "https://api.github.com/repos/muesli/obs-cli/releases/assets/55248889",
      "id": 55248889,
      "node_id": "RA_kwDODjSTC84DSwf5",
      "name": "obs-cli_0.5.0_freebsd_armv6.tar.gz",
      "label": "",
      "uploader": {
        "login": "muesli",
        "id": 146378,
        "node_id": "MDQ6VXNlcjE0NjM3OA==",
        "avatar_url": "https://avatars.githubusercontent.com/u/146378?v=4",
        "gravatar_id": "",
        "url": "https://api.github.com/users/muesli",
        "html_url": "https://github.com/muesli",
        "followers_url": "https://api.github.com/users/muesli/followers",
        "following_url": "https://api.github.com/users/muesli/following{/other_user}",
        "gists_url": "https://api.github.com/users/muesli/gists{/gist_id}",
        "starred_url": "https://api.github.com/users/muesli/starred{/owner}{/repo}",
        "subscriptions_url": "https://api.github.com/users/muesli/subscriptions",
        "organizations_url": "https://api.github.com/users/muesli/orgs",
        "repos_url": "https://api.github.com/users/muesli/repos",
        "events_url": "https://api.github.com/users/muesli/events{/privacy}",
        "received_events_url": "https://api.github.com/users/muesli/received_events",
        "type": "User",
        "site_admin": false
      },
      "content_type": "application/gzip",
      "state": "uploaded",
      "size": 2266711,
      "download_count": 3,
      "created_at": "2022-01-28T23:43:07Z",
      "updated_at": "2022-01-28T23:43:17Z",
      "browser_download_url": "https://github.com/muesli/obs-cli/releases/download/v0.5.0/obs-cli_0.5.0_freebsd_armv6.tar.gz"
    },
    {
      "url": "https://api.github.com/repos/muesli/obs-cli/releases/assets/55248923",
      "id": 55248923,
      "node_id": "RA_kwDODjSTC84DSwgb",
      "name": "obs-cli_0.5.0_freebsd_armv7.tar.gz",
      "label": "",
      "uploader": {
        "login": "muesli",
        "id": 146378,
        "node_id": "MDQ6VXNlcjE0NjM3OA==",
        "avatar_url": "https://avatars.githubusercontent.com/u/146378?v=4",
        "gravatar_id": "",
        "url": "https://api.github.com/users/muesli",
        "html_url": "https://github.com/muesli",
        "followers_url": "https://api.github.com/users/muesli/followers",
        "following_url": "https://api.github.com/users/muesli/following{/other_user}",
        "gists_url": "https://api.github.com/users/muesli/gists{/gist_id}",
        "starred_url": "https://api.github.com/users/muesli/starred{/owner}{/repo}",
        "subscriptions_url": "https://api.github.com/users/muesli/subscriptions",
        "organizations_url": "https://api.github.com/users/muesli/orgs",
        "repos_url": "https://api.github.com/users/muesli/repos",
        "events_url": "https://api.github.com/users/muesli/events{/privacy}",
        "received_events_url": "https://api.github.com/users/muesli/received_events",
        "type": "User",
        "site_admin": false
      },
      "content_type": "application/gzip",
      "state": "uploaded",
      "size": 2263474,
      "download_count": 3,
      "created_at": "2022-01-28T23:43:19Z",
      "updated_at": "2022-01-28T23:43:29Z",
      "browser_download_url": "https://github.com/muesli/obs-cli/releases/download/v0.5.0/obs-cli_0.5.0_freebsd_armv7.tar.gz"
    },
    {
      "url": "https://api.github.com/repos/muesli/obs-cli/releases/assets/55248903",
      "id": 55248903,
      "node_id": "RA_kwDODjSTC84DSwgH",
      "name": "obs-cli_0.5.0_freebsd_i386.tar.gz",
      "label": "",
      "uploader": {
        "login": "muesli",
        "id": 146378,
        "node_id": "MDQ6VXNlcjE0NjM3OA==",
        "avatar_url": "https://avatars.githubusercontent.com/u/146378?v=4",
        "gravatar_id": "",
        "url": "https://api.github.com/users/muesli",
        "html_url": "https://github.com/muesli",
        "followers_url": "https://api.github.com/users/muesli/followers",
        "following_url": "https://api.github.com/users/muesli/following{/other_user}",
        "gists_url": "https://api.github.com/users/muesli/gists{/gist_id}",
        "starred_url": "https://api.github.com/users/muesli/starred{/owner}{/repo}",
        "subscriptions_url": "https://api.github.com/users/muesli/subscriptions",
        "organizations_url": "https://api.github.com/users/muesli/orgs",
        "repos_url": "https://api.github.com/users/muesli/repos",
        "events_url": "https://api.github.com/users/muesli/events{/privacy}",
        "received_events_url": "https://api.github.com/users/muesli/received_events",
        "type": "User",
        "site_admin": false
      },
      "content_type": "application/gzip",
      "state": "uploaded",
      "size": 2287844,
      "download_count": 2,
      "created_at": "2022-01-28T23:43:08Z",
      "updated_at": "2022-01-28T23:43:18Z",
      "browser_download_url": "https://github.com/muesli/obs-cli/releases/download/v0.5.0/obs-cli_0.5.0_freebsd_i386.tar.gz"
    },
    {
      "url": "https://api.github.com/repos/muesli/obs-cli/releases/assets/55248890",
      "id": 55248890,
      "node_id": "RA_kwDODjSTC84DSwf6",
      "name": "obs-cli_0.5.0_freebsd_x86_64.tar.gz",
      "label": "",
      "uploader": {
        "login": "muesli",
        "id": 146378,
        "node_id": "MDQ6VXNlcjE0NjM3OA==",
        "avatar_url": "https://avatars.githubusercontent.com/u/146378?v=4",
        "gravatar_id": "",
        "url": "https://api.github.com/users/muesli",
        "html_url": "https://github.com/muesli",
        "followers_url": "https://api.github.com/users/muesli/followers",
        "following_url": "https://api.github.com/users/muesli/following{/other_user}",
        "gists_url": "https://api.github.com/users/muesli/gists{/gist_id}",
        "starred_url": "https://api.github.com/users/muesli/starred{/owner}{/repo}",
        "subscriptions_url": "https://api.github.com/users/muesli/subscriptions",
        "organizations_url": "https://api.github.com/users/muesli/orgs",
        "repos_url": "https://api.github.com/users/muesli/repos",
        "events_url": "https://api.github.com/users/muesli/events{/privacy}",
        "received_events_url": "https://api.github.com/users/muesli/received_events",
        "type": "User",
        "site_admin": false
      },
      "content_type": "application/gzip",
      "state": "uploaded",
      "size": 2489029,
      "download_count": 4,
      "created_at": "2022-01-28T23:43:07Z",
      "updated_at": "2022-01-28T23:43:17Z",
      "browser_download_url": "https://github.com/muesli/obs-cli/releases/download/v0.5.0/obs-cli_0.5.0_freebsd_x86_64.tar.gz"
    },
    {
      "url": "https://api.github.com/repos/muesli/obs-cli/releases/assets/55248900",
      "id": 55248900,
      "node_id": "RA_kwDODjSTC84DSwgE",
      "name": "obs-cli_0.5.0_linux_386.apk",
      "label": "",
      "uploader": {
        "login": "muesli",
        "id": 146378,
        "node_id": "MDQ6VXNlcjE0NjM3OA==",
        "avatar_url": "https://avatars.githubusercontent.com/u/146378?v=4",
        "gravatar_id": "",
        "url": "https://api.github.com/users/muesli",
        "html_url": "https://github.com/muesli",
        "followers_url": "https://api.github.com/users/muesli/followers",
        "following_url": "https://api.github.com/users/muesli/following{/other_user}",
        "gists_url": "https://api.github.com/users/muesli/gists{/gist_id}",
        "starred_url": "https://api.github.com/users/muesli/starred{/owner}{/repo}",
        "subscriptions_url": "https://api.github.com/users/muesli/subscriptions",
        "organizations_url": "https://api.github.com/users/muesli/orgs",
        "repos_url": "https://api.github.com/users/muesli/repos",
        "events_url": "https://api.github.com/users/muesli/events{/privacy}",
        "received_events_url": "https://api.github.com/users/muesli/received_events",
        "type": "User",
        "site_admin": false
      },
      "content_type": "application/vnd.android.package-archive",
      "state": "uploaded",
      "size": 2283372,
      "download_count": 10,
      "created_at": "2022-01-28T23:43:07Z",
      "updated_at": "2022-01-28T23:43:18Z",
      "browser_download_url": "https://github.com/muesli/obs-cli/releases/download/v0.5.0/obs-cli_0.5.0_linux_386.apk"
    },
    {
      "url": "https://api.github.com/repos/muesli/obs-cli/releases/assets/55248924",
      "id": 55248924,
      "node_id": "RA_kwDODjSTC84DSwgc",
      "name": "obs-cli_0.5.0_linux_386.deb",
      "label": "",
      "uploader": {
        "login": "muesli",
        "id": 146378,
        "node_id": "MDQ6VXNlcjE0NjM3OA==",
        "avatar_url": "https://avatars.githubusercontent.com/u/146378?v=4",
        "gravatar_id": "",
        "url": "https://api.github.com/users/muesli",
        "html_url": "https://github.com/muesli",
        "followers_url": "https://api.github.com/users/muesli/followers",
        "following_url": "https://api.github.com/users/muesli/following{/other_user}",
        "gists_url": "https://api.github.com/users/muesli/gists{/gist_id}",
        "starred_url": "https://api.github.com/users/muesli/starred{/owner}{/repo}",
        "subscriptions_url": "https://api.github.com/users/muesli/subscriptions",
        "organizations_url": "https://api.github.com/users/muesli/orgs",
        "repos_url": "https://api.github.com/users/muesli/repos",
        "events_url": "https://api.github.com/users/muesli/events{/privacy}",
        "received_events_url": "https://api.github.com/users/muesli/received_events",
        "type": "User",
        "site_admin": false
      },
      "content_type": "application/vnd.debian.binary-package",
      "state": "uploaded",
      "size": 2283522,
      "download_count": 33,
      "created_at": "2022-01-28T23:43:19Z",
      "updated_at": "2022-01-28T23:43:28Z",
      "browser_download_url": "https://github.com/muesli/obs-cli/releases/download/v0.5.0/obs-cli_0.5.0_linux_386.deb"
    },
    {
      "url": "https://api.github.com/repos/muesli/obs-cli/releases/assets/55248922",
      "id": 55248922,
      "node_id": "RA_kwDODjSTC84DSwga",
      "name": "obs-cli_0.5.0_linux_386.rpm",
      "label": "",
      "uploader": {
        "login": "muesli",
        "id": 146378,
        "node_id": "MDQ6VXNlcjE0NjM3OA==",
        "avatar_url": "https://avatars.githubusercontent.com/u/146378?v=4",
        "gravatar_id": "",
        "url": "https://api.github.com/users/muesli",
        "html_url": "https://github.com/muesli",
        "followers_url": "https://api.github.com/users/muesli/followers",
        "following_url": "https://api.github.com/users/muesli/following{/other_user}",
        "gists_url": "https://api.github.com/users/muesli/gists{/gist_id}",
        "starred_url": "https://api.github.com/users/muesli/starred{/owner}{/repo}",
        "subscriptions_url": "https://api.github.com/users/muesli/subscriptions",
        "organizations_url": "https://api.github.com/users/muesli/orgs",
        "repos_url": "https://api.github.com/users/muesli/repos",
        "events_url": "https://api.github.com/users/muesli/events{/privacy}",
        "received_events_url": "https://api.github.com/users/muesli/received_events",
        "type": "User",
        "site_admin": false
      },
      "content_type": "application/x-rpm",
      "state": "uploaded",
      "size": 2281019,
      "download_count": 10,
      "created_at": "2022-01-28T23:43:19Z",
      "updated_at": "2022-01-28T23:43:28Z",
      "browser_download_url": "https://github.com/muesli/obs-cli/releases/download/v0.5.0/obs-cli_0.5.0_linux_386.rpm"
    },
    {
      "url": "https://api.github.com/repos/muesli/obs-cli/releases/assets/55248917",
      "id": 55248917,
      "node_id": "RA_kwDODjSTC84DSwgV",
      "name": "obs-cli_0.5.0_linux_amd64.apk",
      "label": "",
      "uploader": {
        "login": "muesli",
        "id": 146378,
        "node_id": "MDQ6VXNlcjE0NjM3OA==",
        "avatar_url": "https://avatars.githubusercontent.com/u/146378?v=4",
        "gravatar_id": "",
        "url": "https://api.github.com/users/muesli",
        "html_url": "https://github.com/muesli",
        "followers_url": "https://api.github.com/users/muesli/followers",
        "following_url": "https://api.github.com/users/muesli/following{/other_user}",
        "gists_url": "https://api.github.com/users/muesli/gists{/gist_id}",
        "starred_url": "https://api.github.com/users/muesli/starred{/owner}{/repo}",
        "subscriptions_url": "https://api.github.com/users/muesli/subscriptions",
        "organizations_url": "https://api.github.com/users/muesli/orgs",
        "repos_url": "https://api.github.com/users/muesli/repos",
        "events_url": "https://api.github.com/users/muesli/events{/privacy}",
        "received_events_url": "https://api.github.com/users/muesli/received_events",
        "type": "User",
        "site_admin": false
      },
      "content_type": "application/vnd.android.package-archive",
      "state": "uploaded",
      "size": 2455866,
      "download_count": 10,
      "created_at": "2022-01-28T23:43:18Z",
      "updated_at": "2022-01-28T23:43:27Z",
      "browser_download_url": "https://github.com/muesli/obs-cli/releases/download/v0.5.0/obs-cli_0.5.0_linux_amd64.apk"
    },
    {
      "url": "https://api.github.com/repos/muesli/obs-cli/releases/assets/55248913",
      "id": 55248913,
      "node_id": "RA_kwDODjSTC84DSwgR",
      "name": "obs-cli_0.5.0_linux_amd64.deb",
      "label": "",
      "uploader": {
        "login": "muesli",
        "id": 146378,
        "node_id": "MDQ6VXNlcjE0NjM3OA==",
        "avatar_url": "https://avatars.githubusercontent.com/u/146378?v=4",
        "gravatar_id": "",
        "url": "https://api.github.com/users/muesli",
        "html_url": "https://github.com/muesli",
        "followers_url": "https://api.github.com/users/muesli/followers",
        "following_url": "https://api.github.com/users/muesli/following{/other_user}",
        "gists_url": "https://api.github.com/users/muesli/gists{/gist_id}",
        "starred_url": "https://api.github.com/users/muesli/starred{/owner}{/repo}",
        "subscriptions_url": "https://api.github.com/users/muesli/subscriptions",
        "organizations_url": "https://api.github.com/users/muesli/orgs",
        "repos_url": "https://api.github.com/users/muesli/repos",
        "events_url": "https://api.github.com/users/muesli/events{/privacy}",
        "received_events_url": "https://api.github.com/users/muesli/received_events",
        "type": "User",
        "site_admin": false
      },
      "content_type": "application/vnd.debian.binary-package",
      "state": "uploaded",
      "size": 2455908,
      "download_count": 305,
      "created_at": "2022-01-28T23:43:18Z",
      "updated_at": "2022-01-28T23:43:26Z",
      "browser_download_url": "https://github.com/muesli/obs-cli/releases/download/v0.5.0/obs-cli_0.5.0_linux_amd64.deb"
    },
    {
      "url": "https://api.github.com/repos/muesli/obs-cli/releases/assets/55248919",
      "id": 55248919,
      "node_id": "RA_kwDODjSTC84DSwgX",
      "name": "obs-cli_0.5.0_linux_amd64.rpm",
      "label": "",
      "uploader": {
        "login": "muesli",
        "id": 146378,
        "node_id": "MDQ6VXNlcjE0NjM3OA==",
        "avatar_url": "https://avatars.githubusercontent.com/u/146378?v=4",
        "gravatar_id": "",
        "url": "https://api.github.com/users/muesli",
        "html_url": "https://github.com/muesli",
        "followers_url": "https://api.github.com/users/muesli/followers",
        "following_url": "https://api.github.com/users/muesli/following{/other_user}",
        "gists_url": "https://api.github.com/users/muesli/gists{/gist_id}",
        "starred_url": "https://api.github.com/users/muesli/starred{/owner}{/repo}",
        "subscriptions_url": "https://api.github.com/users/muesli/subscriptions",
        "organizations_url": "https://api.github.com/users/muesli/orgs",
        "repos_url": "https://api.github.com/users/muesli/repos",
        "events_url": "https://api.github.com/users/muesli/events{/privacy}",
        "received_events_url": "https://api.github.com/users/muesli/received_events",
        "type": "User",
        "site_admin": false
      },
      "content_type": "application/x-rpm",
      "state": "uploaded",
      "size": 2450970,
      "download_count": 69,
      "created_at": "2022-01-28T23:43:19Z",
      "updated_at": "2022-01-28T23:43:28Z",
      "browser_download_url": "https://github.com/muesli/obs-cli/releases/download/v0.5.0/obs-cli_0.5.0_linux_amd64.rpm"
    },
    {
      "url": "https://api.github.com/repos/muesli/obs-cli/releases/assets/55248893",
      "id": 55248893,
      "node_id": "RA_kwDODjSTC84DSwf9",
      "name": "obs-cli_0.5.0_linux_arm64.apk",
      "label": "",
      "uploader": {
        "login": "muesli",
        "id": 146378,
        "node_id": "MDQ6VXNlcjE0NjM3OA==",
        "avatar_url": "https://avatars.githubusercontent.com/u/146378?v=4",
        "gravatar_id": "",
        "url": "https://api.github.com/users/muesli",
        "html_url": "https://github.com/muesli",
        "followers_url": "https://api.github.com/users/muesli/followers",
        "following_url": "https://api.github.com/users/muesli/following{/other_user}",
        "gists_url": "https://api.github.com/users/muesli/gists{/gist_id}",
        "starred_url": "https://api.github.com/users/muesli/starred{/owner}{/repo}",
        "subscriptions_url": "https://api.github.com/users/muesli/subscriptions",
        "organizations_url": "https://api.github.com/users/muesli/orgs",
        "repos_url": "https://api.github.com/users/muesli/repos",
        "events_url": "https://api.github.com/users/muesli/events{/privacy}",
        "received_events_url": "https://api.github.com/users/muesli/received_events",
        "type": "User",
        "site_admin": false
      },
      "content_type": "application/vnd.android.package-archive",
      "state": "uploaded",
      "size": 2259177,
      "download_count": 6,
      "created_at": "2022-01-28T23:43:07Z",
      "updated_at": "2022-01-28T23:43:18Z",
      "browser_download_url": "https://github.com/muesli/obs-cli/releases/download/v0.5.0/obs-cli_0.5.0_linux_arm64.apk"
    },
    {
      "url": "https://api.github.com/repos/muesli/obs-cli/releases/assets/55248892",
      "id": 55248892,
      "node_id": "RA_kwDODjSTC84DSwf8",
      "name": "obs-cli_0.5.0_linux_arm64.deb",
      "label": "",
      "uploader": {
        "login": "muesli",
        "id": 146378,
        "node_id": "MDQ6VXNlcjE0NjM3OA==",
        "avatar_url": "https://avatars.githubusercontent.com/u/146378?v=4",
        "gravatar_id": "",
        "url": "https://api.github.com/users/muesli",
        "html_url": "https://github.com/muesli",
        "followers_url": "https://api.github.com/users/muesli/followers",
        "following_url": "https://api.github.com/users/muesli/following{/other_user}",
        "gists_url": "https://api.github.com/users/muesli/gists{/gist_id}",
        "starred_url": "https://api.github.com/users/muesli/starred{/owner}{/repo}",
        "subscriptions_url": "https://api.github.com/users/muesli/subscriptions",
        "organizations_url": "https://api.github.com/users/muesli/orgs",
        "repos_url": "https://api.github.com/users/muesli/repos",
        "events_url": "https://api.github.com/users/muesli/events{/privacy}",
        "received_events_url": "https://api.github.com/users/muesli/received_events",
        "type": "User",
        "site_admin": false
      },
      "content_type": "application/vnd.debian.binary-package",
      "state": "uploaded",
      "size": 2259274,
      "download_count": 37,
      "created_at": "2022-01-28T23:43:07Z",
      "updated_at": "2022-01-28T23:43:17Z",
      "browser_download_url": "https://github.com/muesli/obs-cli/releases/download/v0.5.0/obs-cli_0.5.0_linux_arm64.deb"
    },
    {
      "url": "https://api.github.com/repos/muesli/obs-cli/releases/assets/55248921",
      "id": 55248921,
      "node_id": "RA_kwDODjSTC84DSwgZ",
      "name": "obs-cli_0.5.0_linux_arm64.rpm",
      "label": "",
      "uploader": {
        "login": "muesli",
        "id": 146378,
        "node_id": "MDQ6VXNlcjE0NjM3OA==",
        "avatar_url": "https://avatars.githubusercontent.com/u/146378?v=4",
        "gravatar_id": "",
        "url": "https://api.github.com/users/muesli",
        "html_url": "https://github.com/muesli",
        "followers_url": "https://api.github.com/users/muesli/followers",
        "following_url": "https://api.github.com/users/muesli/following{/other_user}",
        "gists_url": "https://api.github.com/users/muesli/gists{/gist_id}",
        "starred_url": "https://api.github.com/users/muesli/starred{/owner}{/repo}",
        "subscriptions_url": "https://api.github.com/users/muesli/subscriptions",
        "organizations_url": "https://api.github.com/users/muesli/orgs",
        "repos_url": "https://api.github.com/users/muesli/repos",
        "events_url": "https://api.github.com/users/muesli/events{/privacy}",
        "received_events_url": "https://api.github.com/users/muesli/received_events",
        "type": "User",
        "site_admin": false
      },
      "content_type": "application/x-rpm",
      "state": "uploaded",
      "size": 2256314,
      "download_count": 8,
      "created_at": "2022-01-28T23:43:19Z",
      "updated_at": "2022-01-28T23:43:27Z",
      "browser_download_url": "https://github.com/muesli/obs-cli/releases/download/v0.5.0/obs-cli_0.5.0_linux_arm64.rpm"
    },
    {
      "url": "https://api.github.com/repos/muesli/obs-cli/releases/assets/55248911",
      "id": 55248911,
      "node_id": "RA_kwDODjSTC84DSwgP",
      "name": "obs-cli_0.5.0_linux_arm64.tar.gz",
      "label": "",
      "uploader": {
        "login": "muesli",
        "id": 146378,
        "node_id": "MDQ6VXNlcjE0NjM3OA==",
        "avatar_url": "https://avatars.githubusercontent.com/u/146378?v=4",
        "gravatar_id": "",
        "url": "https://api.github.com/users/muesli",
        "html_url": "https://github.com/muesli",
        "followers_url": "https://api.github.com/users/muesli/followers",
        "following_url": "https://api.github.com/users/muesli/following{/other_user}",
        "gists_url": "https://api.github.com/users/muesli/gists{/gist_id}",
        "starred_url": "https://api.github.com/users/muesli/starred{/owner}{/repo}",
        "subscriptions_url": "https://api.github.com/users/muesli/subscriptions",
        "organizations_url": "https://api.github.com/users/muesli/orgs",
        "repos_url": "https://api.github.com/users/muesli/repos",
        "events_url": "https://api.github.com/users/muesli/events{/privacy}",
        "received_events_url": "https://api.github.com/users/muesli/received_events",
        "type": "User",
        "site_admin": false
      },
      "content_type": "application/gzip",
      "state": "uploaded",
      "size": 2256275,
      "download_count": 6,
      "created_at": "2022-01-28T23:43:18Z",
      "updated_at": "2022-01-28T23:43:26Z",
      "browser_download_url": "https://github.com/muesli/obs-cli/releases/download/v0.5.0/obs-cli_0.5.0_linux_arm64.tar.gz"
    },
    {
      "url": "https://api.github.com/repos/muesli/obs-cli/releases/assets/55248915",
      "id": 55248915,
      "node_id": "RA_kwDODjSTC84DSwgT",
      "name": "obs-cli_0.5.0_linux_armv6.apk",
      "label": "",
      "uploader": {
        "login": "muesli",
        "id": 146378,
        "node_id": "MDQ6VXNlcjE0NjM3OA==",
        "avatar_url": "https://avatars.githubusercontent.com/u/146378?v=4",
        "gravatar_id": "",
        "url": "https://api.github.com/users/muesli",
        "html_url": "https://github.com/muesli",
        "followers_url": "https://api.github.com/users/muesli/followers",
        "following_url": "https://api.github.com/users/muesli/following{/other_user}",
        "gists_url": "https://api.github.com/users/muesli/gists{/gist_id}",
        "starred_url": "https://api.github.com/users/muesli/starred{/owner}{/repo}",
        "subscriptions_url": "https://api.github.com/users/muesli/subscriptions",
        "organizations_url": "https://api.github.com/users/muesli/orgs",
        "repos_url": "https://api.github.com/users/muesli/repos",
        "events_url": "https://api.github.com/users/muesli/events{/privacy}",
        "received_events_url": "https://api.github.com/users/muesli/received_events",
        "type": "User",
        "site_admin": false
      },
      "content_type": "application/vnd.android.package-archive",
      "state": "uploaded",
      "size": 2256688,
      "download_count": 2,
      "created_at": "2022-01-28T23:43:18Z",
      "updated_at": "2022-01-28T23:43:27Z",
      "browser_download_url": "https://github.com/muesli/obs-cli/releases/download/v0.5.0/obs-cli_0.5.0_linux_armv6.apk"
    },
    {
      "url": "https://api.github.com/repos/muesli/obs-cli/releases/assets/55248880",
      "id": 55248880,
      "node_id": "RA_kwDODjSTC84DSwfw",
      "name": "obs-cli_0.5.0_linux_armv6.deb",
      "label": "",
      "uploader": {
        "login": "muesli",
        "id": 146378,
        "node_id": "MDQ6VXNlcjE0NjM3OA==",
        "avatar_url": "https://avatars.githubusercontent.com/u/146378?v=4",
        "gravatar_id": "",
        "url": "https://api.github.com/users/muesli",
        "html_url": "https://github.com/muesli",
        "followers_url": "https://api.github.com/users/muesli/followers",
        "following_url": "https://api.github.com/users/muesli/following{/other_user}",
        "gists_url": "https://api.github.com/users/muesli/gists{/gist_id}",
        "starred_url": "https://api.github.com/users/muesli/starred{/owner}{/repo}",
        "subscriptions_url": "https://api.github.com/users/muesli/subscriptions",
        "organizations_url": "https://api.github.com/users/muesli/orgs",
        "repos_url": "https://api.github.com/users/muesli/repos",
        "events_url": "https://api.github.com/users/muesli/events{/privacy}",
        "received_events_url": "https://api.github.com/users/muesli/received_events",
        "type": "User",
        "site_admin": false
      },
      "content_type": "application/vnd.debian.binary-package",
      "state": "uploaded",
      "size": 2256684,
      "download_count": 3,
      "created_at": "2022-01-28T23:43:07Z",
      "updated_at": "2022-01-28T23:43:19Z",
      "browser_download_url": "https://github.com/muesli/obs-cli/releases/download/v0.5.0/obs-cli_0.5.0_linux_armv6.deb"
    },
    {
      "url": "https://api.github.com/repos/muesli/obs-cli/releases/assets/55248918",
      "id": 55248918,
      "node_id": "RA_kwDODjSTC84DSwgW",
      "name": "obs-cli_0.5.0_linux_armv6.rpm",
      "label": "",
      "uploader": {
        "login": "muesli",
        "id": 146378,
        "node_id": "MDQ6VXNlcjE0NjM3OA==",
        "avatar_url": "https://avatars.githubusercontent.com/u/146378?v=4",
        "gravatar_id": "",
        "url": "https://api.github.com/users/muesli",
        "html_url": "https://github.com/muesli",
        "followers_url": "https://api.github.com/users/muesli/followers",
        "following_url": "https://api.github.com/users/muesli/following{/other_user}",
        "gists_url": "https://api.github.com/users/muesli/gists{/gist_id}",
        "starred_url": "https://api.github.com/users/muesli/starred{/owner}{/repo}",
        "subscriptions_url": "https://api.github.com/users/muesli/subscriptions",
        "organizations_url": "https://api.github.com/users/muesli/orgs",
        "repos_url": "https://api.github.com/users/muesli/repos",
        "events_url": "https://api.github.com/users/muesli/events{/privacy}",
        "received_events_url": "https://api.github.com/users/muesli/received_events",
        "type": "User",
        "site_admin": false
      },
      "content_type": "application/x-rpm",
      "state": "uploaded",
      "size": 2254999,
      "download_count": 2,
      "created_at": "2022-01-28T23:43:18Z",
      "updated_at": "2022-01-28T23:43:26Z",
      "browser_download_url": "https://github.com/muesli/obs-cli/releases/download/v0.5.0/obs-cli_0.5.0_linux_armv6.rpm"
    },
    {
      "url": "https://api.github.com/repos/muesli/obs-cli/releases/assets/55248898",
      "id": 55248898,
      "node_id": "RA_kwDODjSTC84DSwgC",
      "name": "obs-cli_0.5.0_linux_armv6.tar.gz",
      "label": "",
      "uploader": {
        "login": "muesli",
        "id": 146378,
        "node_id": "MDQ6VXNlcjE0NjM3OA==",
        "avatar_url": "https://avatars.githubusercontent.com/u/146378?v=4",
        "gravatar_id": "",
        "url": "https://api.github.com/users/muesli",
        "html_url": "https://github.com/muesli",
        "followers_url": "https://api.github.com/users/muesli/followers",
        "following_url": "https://api.github.com/users/muesli/following{/other_user}",
        "gists_url": "https://api.github.com/users/muesli/gists{/gist_id}",
        "starred_url": "https://api.github.com/users/muesli/starred{/owner}{/repo}",
        "subscriptions_url": "https://api.github.com/users/muesli/subscriptions",
        "organizations_url": "https://api.github.com/users/muesli/orgs",
        "repos_url": "https://api.github.com/users/muesli/repos",
        "events_url": "https://api.github.com/users/muesli/events{/privacy}",
        "received_events_url": "https://api.github.com/users/muesli/received_events",
        "type": "User",
        "site_admin": false
      },
      "content_type": "application/gzip",
      "state": "uploaded",
      "size": 2255941,
      "download_count": 2,
      "created_at": "2022-01-28T23:43:07Z",
      "updated_at": "2022-01-28T23:43:17Z",
      "browser_download_url": "https://github.com/muesli/obs-cli/releases/download/v0.5.0/obs-cli_0.5.0_linux_armv6.tar.gz"
    },
    {
      "url": "https://api.github.com/repos/muesli/obs-cli/releases/assets/55248886",
      "id": 55248886,
      "node_id": "RA_kwDODjSTC84DSwf2",
      "name": "obs-cli_0.5.0_linux_armv7.apk",
      "label": "",
      "uploader": {
        "login": "muesli",
        "id": 146378,
        "node_id": "MDQ6VXNlcjE0NjM3OA==",
        "avatar_url": "https://avatars.githubusercontent.com/u/146378?v=4",
        "gravatar_id": "",
        "url": "https://api.github.com/users/muesli",
        "html_url": "https://github.com/muesli",
        "followers_url": "https://api.github.com/users/muesli/followers",
        "following_url": "https://api.github.com/users/muesli/following{/other_user}",
        "gists_url": "https://api.github.com/users/muesli/gists{/gist_id}",
        "starred_url": "https://api.github.com/users/muesli/starred{/owner}{/repo}",
        "subscriptions_url": "https://api.github.com/users/muesli/subscriptions",
        "organizations_url": "https://api.github.com/users/muesli/orgs",
        "repos_url": "https://api.github.com/users/muesli/repos",
        "events_url": "https://api.github.com/users/muesli/events{/privacy}",
        "received_events_url": "https://api.github.com/users/muesli/received_events",
        "type": "User",
        "site_admin": false
      },
      "content_type": "application/vnd.android.package-archive",
      "state": "uploaded",
      "size": 2253854,
      "download_count": 2,
      "created_at": "2022-01-28T23:43:07Z",
      "updated_at": "2022-01-28T23:43:17Z",
      "browser_download_url": "https://github.com/muesli/obs-cli/releases/download/v0.5.0/obs-cli_0.5.0_linux_armv7.apk"
    },
    {
      "url": "https://api.github.com/repos/muesli/obs-cli/releases/assets/55248902",
      "id": 55248902,
      "node_id": "RA_kwDODjSTC84DSwgG",
      "name": "obs-cli_0.5.0_linux_armv7.deb",
      "label": "",
      "uploader": {
        "login": "muesli",
        "id": 146378,
        "node_id": "MDQ6VXNlcjE0NjM3OA==",
        "avatar_url": "https://avatars.githubusercontent.com/u/146378?v=4",
        "gravatar_id": "",
        "url": "https://api.github.com/users/muesli",
        "html_url": "https://github.com/muesli",
        "followers_url": "https://api.github.com/users/muesli/followers",
        "following_url": "https://api.github.com/users/muesli/following{/other_user}",
        "gists_url": "https://api.github.com/users/muesli/gists{/gist_id}",
        "starred_url": "https://api.github.com/users/muesli/starred{/owner}{/repo}",
        "subscriptions_url": "https://api.github.com/users/muesli/subscriptions",
        "organizations_url": "https://api.github.com/users/muesli/orgs",
        "repos_url": "https://api.github.com/users/muesli/repos",
        "events_url": "https://api.github.com/users/muesli/events{/privacy}",
        "received_events_url": "https://api.github.com/users/muesli/received_events",
        "type": "User",
        "site_admin": false
      },
      "content_type": "application/vnd.debian.binary-package",
      "state": "uploaded",
      "size": 2253996,
      "download_count": 5,
      "created_at": "2022-01-28T23:43:08Z",
      "updated_at": "2022-01-28T23:43:18Z",
      "browser_download_url": "https://github.com/muesli/obs-cli/releases/download/v0.5.0/obs-cli_0.5.0_linux_armv7.deb"
    },
    {
      "url": "https://api.github.com/repos/muesli/obs-cli/releases/assets/55248916",
      "id": 55248916,
      "node_id": "RA_kwDODjSTC84DSwgU",
      "name": "obs-cli_0.5.0_linux_armv7.rpm",
      "label": "",
      "uploader": {
        "login": "muesli",
        "id": 146378,
        "node_id": "MDQ6VXNlcjE0NjM3OA==",
        "avatar_url": "https://avatars.githubusercontent.com/u/146378?v=4",
        "gravatar_id": "",
        "url": "https://api.github.com/users/muesli",
        "html_url": "https://github.com/muesli",
        "followers_url": "https://api.github.com/users/muesli/followers",
        "following_url": "https://api.github.com/users/muesli/following{/other_user}",
        "gists_url": "https://api.github.com/users/muesli/gists{/gist_id}",
        "starred_url": "https://api.github.com/users/muesli/starred{/owner}{/repo}",
        "subscriptions_url": "https://api.github.com/users/muesli/subscriptions",
        "organizations_url": "https://api.github.com/users/muesli/orgs",
        "repos_url": "https://api.github.com/users/muesli/repos",
        "events_url": "https://api.github.com/users/muesli/events{/privacy}",
        "received_events_url": "https://api.github.com/users/muesli/received_events",
        "type": "User",
        "site_admin": false
      },
      "content_type": "application/x-rpm",
      "state": "uploaded",
      "size": 2252679,
      "download_count": 1,
      "created_at": "2022-01-28T23:43:18Z",
      "updated_at": "2022-01-28T23:43:27Z",
      "browser_download_url": "https://github.com/muesli/obs-cli/releases/download/v0.5.0/obs-cli_0.5.0_linux_armv7.rpm"
    },
    {
      "url": "https://api.github.com/repos/muesli/obs-cli/releases/assets/55248895",
      "id": 55248895,
      "node_id": "RA_kwDODjSTC84DSwf_",
      "name": "obs-cli_0.5.0_linux_armv7.tar.gz",
      "label": "",
      "uploader": {
        "login": "muesli",
        "id": 146378,
        "node_id": "MDQ6VXNlcjE0NjM3OA==",
        "avatar_url": "https://avatars.githubusercontent.com/u/146378?v=4",
        "gravatar_id": "",
        "url": "https://api.github.com/users/muesli",
        "html_url": "https://github.com/muesli",
        "followers_url": "https://api.github.com/users/muesli/followers",
        "following_url": "https://api.github.com/users/muesli/following{/other_user}",
        "gists_url": "https://api.github.com/users/muesli/gists{/gist_id}",
        "starred_url": "https://api.github.com/users/muesli/starred{/owner}{/repo}",
        "subscriptions_url": "https://api.github.com/users/muesli/subscriptions",
        "organizations_url": "https://api.github.com/users/muesli/orgs",
        "repos_url": "https://api.github.com/users/muesli/repos",
        "events_url": "https://api.github.com/users/muesli/events{/privacy}",
        "received_events_url": "https://api.github.com/users/muesli/received_events",
        "type": "User",
        "site_admin": false
      },
      "content_type": "application/gzip",
      "state": "uploaded",
      "size": 2253410,
      "download_count": 1,
      "created_at": "2022-01-28T23:43:07Z",
      "updated_at": "2022-01-28T23:43:17Z",
      "browser_download_url": "https://github.com/muesli/obs-cli/releases/download/v0.5.0/obs-cli_0.5.0_linux_armv7.tar.gz"
    },
    {
      "url": "https://api.github.com/repos/muesli/obs-cli/releases/assets/55248899",
      "id": 55248899,
      "node_id": "RA_kwDODjSTC84DSwgD",
      "name": "obs-cli_0.5.0_linux_i386.tar.gz",
      "label": "",
      "uploader": {
        "login": "muesli",
        "id": 146378,
        "node_id": "MDQ6VXNlcjE0NjM3OA==",
        "avatar_url": "https://avatars.githubusercontent.com/u/146378?v=4",
        "gravatar_id": "",
        "url": "https://api.github.com/users/muesli",
        "html_url": "https://github.com/muesli",
        "followers_url": "https://api.github.com/users/muesli/followers",
        "following_url": "https://api.github.com/users/muesli/following{/other_user}",
        "gists_url": "https://api.github.com/users/muesli/gists{/gist_id}",
        "starred_url": "https://api.github.com/users/muesli/starred{/owner}{/repo}",
        "subscriptions_url": "https://api.github.com/users/muesli/subscriptions",
        "organizations_url": "https://api.github.com/users/muesli/orgs",
        "repos_url": "https://api.github.com/users/muesli/repos",
        "events_url": "https://api.github.com/users/muesli/events{/privacy}",
        "received_events_url": "https://api.github.com/users/muesli/received_events",
        "type": "User",
        "site_admin": false
      },
      "content_type": "application/gzip",
      "state": "uploaded",
      "size": 2281736,
      "download_count": 2,
      "created_at": "2022-01-28T23:43:07Z",
      "updated_at": "2022-01-28T23:43:17Z",
      "browser_download_url": "https://github.com/muesli/obs-cli/releases/download/v0.5.0/obs-cli_0.5.0_linux_i386.tar.gz"
    },
    {
      "url": "https://api.github.com/repos/muesli/obs-cli/releases/assets/55248914",
      "id": 55248914,
      "node_id": "RA_kwDODjSTC84DSwgS",
      "name": "obs-cli_0.5.0_linux_x86_64.tar.gz",
      "label": "",
      "uploader": {
        "login": "muesli",
        "id": 146378,
        "node_id": "MDQ6VXNlcjE0NjM3OA==",
        "avatar_url": "https://avatars.githubusercontent.com/u/146378?v=4",
        "gravatar_id": "",
        "url": "https://api.github.com/users/muesli",
        "html_url": "https://github.com/muesli",
        "followers_url": "https://api.github.com/users/muesli/followers",
        "following_url": "https://api.github.com/users/muesli/following{/other_user}",
        "gists_url": "https://api.github.com/users/muesli/gists{/gist_id}",
        "starred_url": "https://api.github.com/users/muesli/starred{/owner}{/repo}",
        "subscriptions_url": "https://api.github.com/users/muesli/subscriptions",
        "organizations_url": "https://api.github.com/users/muesli/orgs",
        "repos_url": "https://api.github.com/users/muesli/repos",
        "events_url": "https://api.github.com/users/muesli/events{/privacy}",
        "received_events_url": "https://api.github.com/users/muesli/received_events",
        "type": "User",
        "site_admin": false
      },
      "content_type": "application/gzip",
      "state": "uploaded",
      "size": 2452524,
      "download_count": 473,
      "created_at": "2022-01-28T23:43:18Z",
      "updated_at": "2022-01-28T23:43:27Z",
      "browser_download_url": "https://github.com/muesli/obs-cli/releases/download/v0.5.0/obs-cli_0.5.0_linux_x86_64.tar.gz"
    },
    {
      "url": "https://api.github.com/repos/muesli/obs-cli/releases/assets/55248894",
      "id": 55248894,
      "node_id": "RA_kwDODjSTC84DSwf-",
      "name": "obs-cli_0.5.0_openbsd_arm64.tar.gz",
      "label": "",
      "uploader": {
        "login": "muesli",
        "id": 146378,
        "node_id": "MDQ6VXNlcjE0NjM3OA==",
        "avatar_url": "https://avatars.githubusercontent.com/u/146378?v=4",
        "gravatar_id": "",
        "url": "https://api.github.com/users/muesli",
        "html_url": "https://github.com/muesli",
        "followers_url": "https://api.github.com/users/muesli/followers",
        "following_url": "https://api.github.com/users/muesli/following{/other_user}",
        "gists_url": "https://api.github.com/users/muesli/gists{/gist_id}",
        "starred_url": "https://api.github.com/users/muesli/starred{/owner}{/repo}",
        "subscriptions_url": "https://api.github.com/users/muesli/subscriptions",
        "organizations_url": "https://api.github.com/users/muesli/orgs",
        "repos_url": "https://api.github.com/users/muesli/repos",
        "events_url": "https://api.github.com/users/muesli/events{/privacy}",
        "received_events_url": "https://api.github.com/users/muesli/received_events",
        "type": "User",
        "site_admin": false
      },
      "content_type": "application/gzip",
      "state": "uploaded",
      "size": 2265659,
      "download_count": 1,
      "created_at": "2022-01-28T23:43:07Z",
      "updated_at": "2022-01-28T23:43:17Z",
      "browser_download_url": "https://github.com/muesli/obs-cli/releases/download/v0.5.0/obs-cli_0.5.0_openbsd_arm64.tar.gz"
    },
    {
      "url": "https://api.github.com/repos/muesli/obs-cli/releases/assets/55248888",
      "id": 55248888,
      "node_id": "RA_kwDODjSTC84DSwf4",
      "name": "obs-cli_0.5.0_openbsd_armv6.tar.gz",
      "label": "",
      "uploader": {
        "login": "muesli",
        "id": 146378,
        "node_id": "MDQ6VXNlcjE0NjM3OA==",
        "avatar_url": "https://avatars.githubusercontent.com/u/146378?v=4",
        "gravatar_id": "",
        "url": "https://api.github.com/users/muesli",
        "html_url": "https://github.com/muesli",
        "followers_url": "https://api.github.com/users/muesli/followers",
        "following_url": "https://api.github.com/users/muesli/following{/other_user}",
        "gists_url": "https://api.github.com/users/muesli/gists{/gist_id}",
        "starred_url": "https://api.github.com/users/muesli/starred{/owner}{/repo}",
        "subscriptions_url": "https://api.github.com/users/muesli/subscriptions",
        "organizations_url": "https://api.github.com/users/muesli/orgs",
        "repos_url": "https://api.github.com/users/muesli/repos",
        "events_url": "https://api.github.com/users/muesli/events{/privacy}",
        "received_events_url": "https://api.github.com/users/muesli/received_events",
        "type": "User",
        "site_admin": false
      },
      "content_type": "application/gzip",
      "state": "uploaded",
      "size": 2265829,
      "download_count": 1,
      "created_at": "2022-01-28T23:43:07Z",
      "updated_at": "2022-01-28T23:43:17Z",
      "browser_download_url": "https://github.com/muesli/obs-cli/releases/download/v0.5.0/obs-cli_0.5.0_openbsd_armv6.tar.gz"
    },
    {
      "url": "https://api.github.com/repos/muesli/obs-cli/releases/assets/55248901",
      "id": 55248901,
      "node_id": "RA_kwDODjSTC84DSwgF",
      "name": "obs-cli_0.5.0_openbsd_armv7.tar.gz",
      "label": "",
      "uploader": {
        "login": "muesli",
        "id": 146378,
        "node_id": "MDQ6VXNlcjE0NjM3OA==",
        "avatar_url": "https://avatars.githubusercontent.com/u/146378?v=4",
        "gravatar_id": "",
        "url": "https://api.github.com/users/muesli",
        "html_url": "https://github.com/muesli",
        "followers_url": "https://api.github.com/users/muesli/followers",
        "following_url": "https://api.github.com/users/muesli/following{/other_user}",
        "gists_url": "https://api.github.com/users/muesli/gists{/gist_id}",
        "starred_url": "https://api.github.com/users/muesli/starred{/owner}{/repo}",
        "subscriptions_url": "https://api.github.com/users/muesli/subscriptions",
        "organizations_url": "https://api.github.com/users/muesli/orgs",
        "repos_url": "https://api.github.com/users/muesli/repos",
        "events_url": "https://api.github.com/users/muesli/events{/privacy}",
        "received_events_url": "https://api.github.com/users/muesli/received_events",
        "type": "User",
        "site_admin": false
      },
      "content_type": "application/gzip",
      "state": "uploaded",
      "size": 2261572,
      "download_count": 1,
      "created_at": "2022-01-28T23:43:08Z",
      "updated_at": "2022-01-28T23:43:18Z",
      "browser_download_url": "https://github.com/muesli/obs-cli/releases/download/v0.5.0/obs-cli_0.5.0_openbsd_armv7.tar.gz"
    },
    {
      "url": "https://api.github.com/repos/muesli/obs-cli/releases/assets/55248885",
      "id": 55248885,
      "node_id": "RA_kwDODjSTC84DSwf1",
      "name": "obs-cli_0.5.0_openbsd_i386.tar.gz",
      "label": "",
      "uploader": {
        "login": "muesli",
        "id": 146378,
        "node_id": "MDQ6VXNlcjE0NjM3OA==",
        "avatar_url": "https://avatars.githubusercontent.com/u/146378?v=4",
        "gravatar_id": "",
        "url": "https://api.github.com/users/muesli",
        "html_url": "https://github.com/muesli",
        "followers_url": "https://api.github.com/users/muesli/followers",
        "following_url": "https://api.github.com/users/muesli/following{/other_user}",
        "gists_url": "https://api.github.com/users/muesli/gists{/gist_id}",
        "starred_url": "https://api.github.com/users/muesli/starred{/owner}{/repo}",
        "subscriptions_url": "https://api.github.com/users/muesli/subscriptions",
        "organizations_url": "https://api.github.com/users/muesli/orgs",
        "repos_url": "https://api.github.com/users/muesli/repos",
        "events_url": "https://api.github.com/users/muesli/events{/privacy}",
        "received_events_url": "https://api.github.com/users/muesli/received_events",
        "type": "User",
        "site_admin": false
      },
      "content_type": "application/gzip",
      "state": "uploaded",
      "size": 2288577,
      "download_count": 1,
      "created_at": "2022-01-28T23:43:07Z",
      "updated_at": "2022-01-28T23:43:17Z",
      "browser_download_url": "https://github.com/muesli/obs-cli/releases/download/v0.5.0/obs-cli_0.5.0_openbsd_i386.tar.gz"
    },
    {
      "url": "https://api.github.com/repos/muesli/obs-cli/releases/assets/55248920",
      "id": 55248920,
      "node_id": "RA_kwDODjSTC84DSwgY",
      "name": "obs-cli_0.5.0_openbsd_x86_64.tar.gz",
      "label": "",
      "uploader": {
        "login": "muesli",
        "id": 146378,
        "node_id": "MDQ6VXNlcjE0NjM3OA==",
        "avatar_url": "https://avatars.githubusercontent.com/u/146378?v=4",
        "gravatar_id": "",
        "url": "https://api.github.com/users/muesli",
        "html_url": "https://github.com/muesli",
        "followers_url": "https://api.github.com/users/muesli/followers",
        "following_url": "https://api.github.com/users/muesli/following{/other_user}",
        "gists_url": "https://api.github.com/users/muesli/gists{/gist_id}",
        "starred_url": "https://api.github.com/users/muesli/starred{/owner}{/repo}",
        "subscriptions_url": "https://api.github.com/users/muesli/subscriptions",
        "organizations_url": "https://api.github.com/users/muesli/orgs",
        "repos_url": "https://api.github.com/users/muesli/repos",
        "events_url": "https://api.github.com/users/muesli/events{/privacy}",
        "received_events_url": "https://api.github.com/users/muesli/received_events",
        "type": "User",
        "site_admin": false
      },
      "content_type": "application/gzip",
      "state": "uploaded",
      "size": 2488144,
      "download_count": 7,
      "created_at": "2022-01-28T23:43:19Z",
      "updated_at": "2022-01-28T23:43:28Z",
      "browser_download_url": "https://github.com/muesli/obs-cli/releases/download/v0.5.0/obs-cli_0.5.0_openbsd_x86_64.tar.gz"
    },
    {
      "url": "https://api.github.com/repos/muesli/obs-cli/releases/assets/55248882",
      "id": 55248882,
      "node_id": "RA_kwDODjSTC84DSwfy",
      "name": "obs-cli_0.5.0_Windows_arm64.zip",
      "label": "",
      "uploader": {
        "login": "muesli",
        "id": 146378,
        "node_id": "MDQ6VXNlcjE0NjM3OA==",
        "avatar_url": "https://avatars.githubusercontent.com/u/146378?v=4",
        "gravatar_id": "",
        "url": "https://api.github.com/users/muesli",
        "html_url": "https://github.com/muesli",
        "followers_url": "https://api.github.com/users/muesli/followers",
        "following_url": "https://api.github.com/users/muesli/following{/other_user}",
        "gists_url": "https://api.github.com/users/muesli/gists{/gist_id}",
        "starred_url": "https://api.github.com/users/muesli/starred{/owner}{/repo}",
        "subscriptions_url": "https://api.github.com/users/muesli/subscriptions",
        "organizations_url": "https://api.github.com/users/muesli/orgs",
        "repos_url": "https://api.github.com/users/muesli/repos",
        "events_url": "https://api.github.com/users/muesli/events{/privacy}",
        "received_events_url": "https://api.github.com/users/muesli/received_events",
        "type": "User",
        "site_admin": false
      },
      "content_type": "application/zip",
      "state": "uploaded",
      "size": 2266676,
      "download_count": 25,
      "created_at": "2022-01-28T23:43:07Z",
      "updated_at": "2022-01-28T23:43:17Z",
      "browser_download_url": "https://github.com/muesli/obs-cli/releases/download/v0.5.0/obs-cli_0.5.0_Windows_arm64.zip"
    },
    {
      "url": "https://api.github.com/repos/muesli/obs-cli/releases/assets/55248891",
      "id": 55248891,
      "node_id": "RA_kwDODjSTC84DSwf7",
      "name": "obs-cli_0.5.0_Windows_armv6.zip",
      "label": "",
      "uploader": {
        "login": "muesli",
        "id": 146378,
        "node_id": "MDQ6VXNlcjE0NjM3OA==",
        "avatar_url": "https://avatars.githubusercontent.com/u/146378?v=4",
        "gravatar_id": "",
        "url": "https://api.github.com/users/muesli",
        "html_url": "https://github.com/muesli",
        "followers_url": "https://api.github.com/users/muesli/followers",
        "following_url": "https://api.github.com/users/muesli/following{/other_user}",
        "gists_url": "https://api.github.com/users/muesli/gists{/gist_id}",
        "starred_url": "https://api.github.com/users/muesli/starred{/owner}{/repo}",
        "subscriptions_url": "https://api.github.com/users/muesli/subscriptions",
        "organizations_url": "https://api.github.com/users/muesli/orgs",
        "repos_url": "https://api.github.com/users/muesli/repos",
        "events_url": "https://api.github.com/users/muesli/events{/privacy}",
        "received_events_url": "https://api.github.com/users/muesli/received_events",
        "type": "User",
        "site_admin": false
      },
      "content_type": "application/zip",
      "state": "uploaded",
      "size": 2298347,
      "download_count": 2,
      "created_at": "2022-01-28T23:43:07Z",
      "updated_at": "2022-01-28T23:43:17Z",
      "browser_download_url": "https://github.com/muesli/obs-cli/releases/download/v0.5.0/obs-cli_0.5.0_Windows_armv6.zip"
    },
    {
      "url": "https://api.github.com/repos/muesli/obs-cli/releases/assets/55248887",
      "id": 55248887,
      "node_id": "RA_kwDODjSTC84DSwf3",
      "name": "obs-cli_0.5.0_Windows_armv7.zip",
      "label": "",
      "uploader": {
        "login": "muesli",
        "id": 146378,
        "node_id": "MDQ6VXNlcjE0NjM3OA==",
        "avatar_url": "https://avatars.githubusercontent.com/u/146378?v=4",
        "gravatar_id": "",
        "url": "https://api.github.com/users/muesli",
        "html_url": "https://github.com/muesli",
        "followers_url": "https://api.github.com/users/muesli/followers",
        "following_url": "https://api.github.com/users/muesli/following{/other_user}",
        "gists_url": "https://api.github.com/users/muesli/gists{/gist_id}",
        "starred_url": "https://api.github.com/users/muesli/starred{/owner}{/repo}",
        "subscriptions_url": "https://api.github.com/users/muesli/subscriptions",
        "organizations_url": "https://api.github.com/users/muesli/orgs",
        "repos_url": "https://api.github.com/users/muesli/repos",
        "events_url": "https://api.github.com/users/muesli/events{/privacy}",
        "received_events_url": "https://api.github.com/users/muesli/received_events",
        "type": "User",
        "site_admin": false
      },
      "content_type": "application/zip",
      "state": "uploaded",
      "size": 2291891,
      "download_count": 2,
      "created_at": "2022-01-28T23:43:07Z",
      "updated_at": "2022-01-28T23:43:17Z",
      "browser_download_url": "https://github.com/muesli/obs-cli/releases/download/v0.5.0/obs-cli_0.5.0_Windows_armv7.zip"
    },
    {
      "url": "https://api.github.com/repos/muesli/obs-cli/releases/assets/55248881",
      "id": 55248881,
      "node_id": "RA_kwDODjSTC84DSwfx",
      "name": "obs-cli_0.5.0_Windows_i386.zip",
      "label": "",
      "uploader": {
        "login": "muesli",
        "id": 146378,
        "node_id": "MDQ6VXNlcjE0NjM3OA==",
        "avatar_url": "https://avatars.githubusercontent.com/u/146378?v=4",
        "gravatar_id": "",
        "url": "https://api.github.com/users/muesli",
        "html_url": "https://github.com/muesli",
        "followers_url": "https://api.github.com/users/muesli/followers",
        "following_url": "https://api.github.com/users/muesli/following{/other_user}",
        "gists_url": "https://api.github.com/users/muesli/gists{/gist_id}",
        "starred_url": "https://api.github.com/users/muesli/starred{/owner}{/repo}",
        "subscriptions_url": "https://api.github.com/users/muesli/subscriptions",
        "organizations_url": "https://api.github.com/users/muesli/orgs",
        "repos_url": "https://api.github.com/users/muesli/repos",
        "events_url": "https://api.github.com/users/muesli/events{/privacy}",
        "received_events_url": "https://api.github.com/users/muesli/received_events",
        "type": "User",
        "site_admin": false
      },
      "content_type": "application/zip",
      "state": "uploaded",
      "size": 2347820,
      "download_count": 6,
      "created_at": "2022-01-28T23:43:07Z",
      "updated_at": "2022-01-28T23:43:18Z",
      "browser_download_url": "https://github.com/muesli/obs-cli/releases/download/v0.5.0/obs-cli_0.5.0_Windows_i386.zip"
    },
    {
      "url": "https://api.github.com/repos/muesli/obs-cli/releases/assets/55248897",
      "id": 55248897,
      "node_id": "RA_kwDODjSTC84DSwgB",
      "name": "obs-cli_0.5.0_Windows_x86_64.zip",
      "label": "",
      "uploader": {
        "login": "muesli",
        "id": 146378,
        "node_id": "MDQ6VXNlcjE0NjM3OA==",
        "avatar_url": "https://avatars.githubusercontent.com/u/146378?v=4",
        "gravatar_id": "",
        "url": "https://api.github.com/users/muesli",
        "html_url": "https://github.com/muesli",
        "followers_url": "https://api.github.com/users/muesli/followers",
        "following_url": "https://api.github.com/users/muesli/following{/other_user}",
        "gists_url": "https://api.github.com/users/muesli/gists{/gist_id}",
        "starred_url": "https://api.github.com/users/muesli/starred{/owner}{/repo}",
        "subscriptions_url": "https://api.github.com/users/muesli/subscriptions",
        "organizations_url": "https://api.github.com/users/muesli/orgs",
        "repos_url": "https://api.github.com/users/muesli/repos",
        "events_url": "https://api.github.com/users/muesli/events{/privacy}",
        "received_events_url": "https://api.github.com/users/muesli/received_events",
        "type": "User",
        "site_admin": false
      },
      "content_type": "application/zip",
      "state": "uploaded",
      "size": 2462677,
      "download_count": 242,
      "created_at": "2022-01-28T23:43:07Z",
      "updated_at": "2022-01-28T23:43:18Z",
      "browser_download_url": "https://github.com/muesli/obs-cli/releases/download/v0.5.0/obs-cli_0.5.0_Windows_x86_64.zip"
    }
  ],
  "tarball_url": "https://api.github.com/repos/muesli/obs-cli/tarball/v0.5.0",
  "zipball_url": "https://api.github.com/repos/muesli/obs-cli/zipball/v0.5.0",
  "body": "## Changelog\n* 6d0b44c Add replay buffer commands\n* 7308a34 Add the \"scene get\" command\n* c15b1ea Add the \"sceneitem visible\" command\n* 703decb Bump goobs to v0.8.0\n* 6bb6b06 Slightly different wording in README\n\n",
  "reactions": {
    "url": "https://api.github.com/repos/muesli/obs-cli/releases/58236917/reactions",
    "total_count": 7,
    "+1": 2,
    "-1": 0,
    "laugh": 1,
    "hooray": 2,
    "confused": 0,
    "heart": 1,
    "rocket": 1,
    "eyes": 0
  }
}
