{
  "url": "https://api.github.com/repos/LizardByte/Sunshine/releases/88260187",
  "assets_url": "https://api.github.com/repos/LizardByte/Sunshine/releases/88260187/assets",
  "upload_url": "https://uploads.github.com/repos/LizardByte/Sunshine/releases/88260187/assets{?name,label}",
  "html_url": "https://github.com/LizardByte/Sunshine/releases/tag/v0.17.0",
  "id": 88260187,
  "author": {
    "login": "LizardByte-bot",
    "id": 108553330,
    "node_id": "U_kgDOBnhkcg",
    "avatar_url": "https://avatars.githubusercontent.com/u/108553330?v=4",
    "gravatar_id": "",
    "url": "https://api.github.com/users/LizardByte-bot",
    "html_url": "https://github.com/LizardByte-bot",
    "followers_url": "https://api.github.com/users/LizardByte-bot/followers",
    "following_url": "https://api.github.com/users/LizardByte-bot/following{/other_user}",
    "gists_url": "https://api.github.com/users/LizardByte-bot/gists{/gist_id}",
    "starred_url": "https://api.github.com/users/LizardByte-bot/starred{/owner}{/repo}",
    "subscriptions_url": "https://api.github.com/users/LizardByte-bot/subscriptions",
    "organizations_url": "https://api.github.com/users/LizardByte-bot/orgs",
    "repos_url": "https://api.github.com/users/LizardByte-bot/repos",
    "events_url": "https://api.github.com/users/LizardByte-bot/events{/privacy}",
    "received_events_url": "https://api.github.com/users/LizardByte-bot/received_events",
    "type": "User",
    "site_admin": false
  },
  "node_id": "RE_kwDOGiedss4FQr5b",
  "tag_name": "v0.17.0",
  "target_commitish": "b2fe0423d2894aed889dd51a83dd361a72bb4231",
  "name": "v0.17.0",
  "draft": false,
  "prerelease": false,
  "created_at": "2023-01-09T02:03:16Z",
  "published_at": "2023-01-09T02:11:51Z",
  "assets": [
    {
      "url": "https://api.github.com/repos/LizardByte/Sunshine/releases/assets/90983339",
      "id": 90983339,
      "node_id": "RA_kwDOGiedss4FbEur",
      "name": "Portfile",
      "label": "",
      "uploader": {
        "login": "LizardByte-bot",
        "id": 108553330,
        "node_id": "U_kgDOBnhkcg",
        "avatar_url": "https://avatars.githubusercontent.com/u/108553330?v=4",
        "gravatar_id": "",
        "url": "https://api.github.com/users/LizardByte-bot",
        "html_url": "https://github.com/LizardByte-bot",
        "followers_url": "https://api.github.com/users/LizardByte-bot/followers",
        "following_url": "https://api.github.com/users/LizardByte-bot/following{/other_user}",
        "gists_url": "https://api.github.com/users/LizardByte-bot/gists{/gist_id}",
        "starred_url": "https://api.github.com/users/LizardByte-bot/starred{/owner}{/repo}",
        "subscriptions_url": "https://api.github.com/users/LizardByte-bot/subscriptions",
        "organizations_url": "https://api.github.com/users/LizardByte-bot/orgs",
        "repos_url": "https://api.github.com/users/LizardByte-bot/repos",
        "events_url": "https://api.github.com/users/LizardByte-bot/events{/privacy}",
        "received_events_url": "https://api.github.com/users/LizardByte-bot/received_events",
        "type": "User",
        "site_admin": false
      },
      "content_type": "raw",
      "state": "uploaded",
      "size": 2826,
      "download_count": 130,
      "created_at": "2023-01-09T02:20:21Z",
      "updated_at": "2023-01-09T02:20:21Z",
      "browser_download_url": "https://github.com/LizardByte/Sunshine/releases/download/v0.17.0/Portfile"
    },
    {
      "url": "https://api.github.com/repos/LizardByte/Sunshine/releases/assets/90982866",
      "id": 90982866,
      "node_id": "RA_kwDOGiedss4FbEnS",
      "name": "sunshine-20.04.deb",
      "label": "",
      "uploader": {
        "login": "LizardByte-bot",
        "id": 108553330,
        "node_id": "U_kgDOBnhkcg",
        "avatar_url": "https://avatars.githubusercontent.com/u/108553330?v=4",
        "gravatar_id": "",
        "url": "https://api.github.com/users/LizardByte-bot",
        "html_url": "https://github.com/LizardByte-bot",
        "followers_url": "https://api.github.com/users/LizardByte-bot/followers",
        "following_url": "https://api.github.com/users/LizardByte-bot/following{/other_user}",
        "gists_url": "https://api.github.com/users/LizardByte-bot/gists{/gist_id}",
        "starred_url": "https://api.github.com/users/LizardByte-bot/starred{/owner}{/repo}",
        "subscriptions_url": "https://api.github.com/users/LizardByte-bot/subscriptions",
        "organizations_url": "https://api.github.com/users/LizardByte-bot/orgs",
        "repos_url": "https://api.github.com/users/LizardByte-bot/repos",
        "events_url": "https://api.github.com/users/LizardByte-bot/events{/privacy}",
        "received_events_url": "https://api.github.com/users/LizardByte-bot/received_events",
        "type": "User",
        "site_admin": false
      },
      "content_type": "raw",
      "state": "uploaded",
      "size": 15136396,
      "download_count": 239,
      "created_at": "2023-01-09T02:11:52Z",
      "updated_at": "2023-01-09T02:11:53Z",
      "browser_download_url": "https://github.com/LizardByte/Sunshine/releases/download/v0.17.0/sunshine-20.04.deb"
    },
    {
      "url": "https://api.github.com/repos/LizardByte/Sunshine/releases/assets/90982878",
      "id": 90982878,
      "node_id": "RA_kwDOGiedss4FbEne",
      "name": "sunshine-22.04.deb",
      "label": "",
      "uploader": {
        "login": "LizardByte-bot",
        "id": 108553330,
        "node_id": "U_kgDOBnhkcg",
        "avatar_url": "https://avatars.githubusercontent.com/u/108553330?v=4",
        "gravatar_id": "",
        "url": "https://api.github.com/users/LizardByte-bot",
        "html_url": "https://github.com/LizardByte-bot",
        "followers_url": "https://api.github.com/users/LizardByte-bot/followers",
        "following_url": "https://api.github.com/users/LizardByte-bot/following{/other_user}",
        "gists_url": "https://api.github.com/users/LizardByte-bot/gists{/gist_id}",
        "starred_url": "https://api.github.com/users/LizardByte-bot/starred{/owner}{/repo}",
        "subscriptions_url": "https://api.github.com/users/LizardByte-bot/subscriptions",
        "organizations_url": "https://api.github.com/users/LizardByte-bot/orgs",
        "repos_url": "https://api.github.com/users/LizardByte-bot/repos",
        "events_url": "https://api.github.com/users/LizardByte-bot/events{/privacy}",
        "received_events_url": "https://api.github.com/users/LizardByte-bot/received_events",
        "type": "User",
        "site_admin": false
      },
      "content_type": "raw",
      "state": "uploaded",
      "size": 15126142,
      "download_count": 509,
      "created_at": "2023-01-09T02:12:14Z",
      "updated_at": "2023-01-09T02:12:15Z",
      "browser_download_url": "https://github.com/LizardByte/Sunshine/releases/download/v0.17.0/sunshine-22.04.deb"
    },
    {
      "url": "https://api.github.com/repos/LizardByte/Sunshine/releases/assets/90983006",
      "id": 90983006,
      "node_id": "RA_kwDOGiedss4FbEpe",
      "name": "sunshine-windows.exe",
      "label": "",
      "uploader": {
        "login": "LizardByte-bot",
        "id": 108553330,
        "node_id": "U_kgDOBnhkcg",
        "avatar_url": "https://avatars.githubusercontent.com/u/108553330?v=4",
        "gravatar_id": "",
        "url": "https://api.github.com/users/LizardByte-bot",
        "html_url": "https://github.com/LizardByte-bot",
        "followers_url": "https://api.github.com/users/LizardByte-bot/followers",
        "following_url": "https://api.github.com/users/LizardByte-bot/following{/other_user}",
        "gists_url": "https://api.github.com/users/LizardByte-bot/gists{/gist_id}",
        "starred_url": "https://api.github.com/users/LizardByte-bot/starred{/owner}{/repo}",
        "subscriptions_url": "https://api.github.com/users/LizardByte-bot/subscriptions",
        "organizations_url": "https://api.github.com/users/LizardByte-bot/orgs",
        "repos_url": "https://api.github.com/users/LizardByte-bot/repos",
        "events_url": "https://api.github.com/users/LizardByte-bot/events{/privacy}",
        "received_events_url": "https://api.github.com/users/LizardByte-bot/received_events",
        "type": "User",
        "site_admin": false
      },
      "content_type": "raw",
      "state": "uploaded",
      "size": 16110458,
      "download_count": 7056,
      "created_at": "2023-01-09T02:14:30Z",
      "updated_at": "2023-01-09T02:14:32Z",
      "browser_download_url": "https://github.com/LizardByte/Sunshine/releases/download/v0.17.0/sunshine-windows.exe"
    },
    {
      "url": "https://api.github.com/repos/LizardByte/Sunshine/releases/assets/90983007",
      "id": 90983007,
      "node_id": "RA_kwDOGiedss4FbEpf",
      "name": "sunshine-windows.zip",
      "label": "",
      "uploader": {
        "login": "LizardByte-bot",
        "id": 108553330,
        "node_id": "U_kgDOBnhkcg",
        "avatar_url": "https://avatars.githubusercontent.com/u/108553330?v=4",
        "gravatar_id": "",
        "url": "https://api.github.com/users/LizardByte-bot",
        "html_url": "https://github.com/LizardByte-bot",
        "followers_url": "https://api.github.com/users/LizardByte-bot/followers",
        "following_url": "https://api.github.com/users/LizardByte-bot/following{/other_user}",
        "gists_url": "https://api.github.com/users/LizardByte-bot/gists{/gist_id}",
        "starred_url": "https://api.github.com/users/LizardByte-bot/starred{/owner}{/repo}",
        "subscriptions_url": "https://api.github.com/users/LizardByte-bot/subscriptions",
        "organizations_url": "https://api.github.com/users/LizardByte-bot/orgs",
        "repos_url": "https://api.github.com/users/LizardByte-bot/repos",
        "events_url": "https://api.github.com/users/LizardByte-bot/events{/privacy}",
        "received_events_url": "https://api.github.com/users/LizardByte-bot/received_events",
        "type": "User",
        "site_admin": false
      },
      "content_type": "raw",
      "state": "uploaded",
      "size": 20534761,
      "download_count": 2633,
      "created_at": "2023-01-09T02:14:32Z",
      "updated_at": "2023-01-09T02:14:33Z",
      "browser_download_url": "https://github.com/LizardByte/Sunshine/releases/download/v0.17.0/sunshine-windows.zip"
    },
    {
      "url": "https://api.github.com/repos/LizardByte/Sunshine/releases/assets/90982954",
      "id": 90982954,
      "node_id": "RA_kwDOGiedss4FbEoq",
      "name": "sunshine.AppImage",
      "label": "",
      "uploader": {
        "login": "LizardByte-bot",
        "id": 108553330,
        "node_id": "U_kgDOBnhkcg",
        "avatar_url": "https://avatars.githubusercontent.com/u/108553330?v=4",
        "gravatar_id": "",
        "url": "https://api.github.com/users/LizardByte-bot",
        "html_url": "https://github.com/LizardByte-bot",
        "followers_url": "https://api.github.com/users/LizardByte-bot/followers",
        "following_url": "https://api.github.com/users/LizardByte-bot/following{/other_user}",
        "gists_url": "https://api.github.com/users/LizardByte-bot/gists{/gist_id}",
        "starred_url": "https://api.github.com/users/LizardByte-bot/starred{/owner}{/repo}",
        "subscriptions_url": "https://api.github.com/users/LizardByte-bot/subscriptions",
        "organizations_url": "https://api.github.com/users/LizardByte-bot/orgs",
        "repos_url": "https://api.github.com/users/LizardByte-bot/repos",
        "events_url": "https://api.github.com/users/LizardByte-bot/events{/privacy}",
        "received_events_url": "https://api.github.com/users/LizardByte-bot/received_events",
        "type": "User",
        "site_admin": false
      },
      "content_type": "raw",
      "state": "uploaded",
      "size": 26727616,
      "download_count": 726,
      "created_at": "2023-01-09T02:13:41Z",
      "updated_at": "2023-01-09T02:13:43Z",
      "browser_download_url": "https://github.com/LizardByte/Sunshine/releases/download/v0.17.0/sunshine.AppImage"
    },
    {
      "url": "https://api.github.com/repos/LizardByte/Sunshine/releases/assets/90983344",
      "id": 90983344,
      "node_id": "RA_kwDOGiedss4FbEuw",
      "name": "sunshine.dmg",
      "label": "",
      "uploader": {
        "login": "LizardByte-bot",
        "id": 108553330,
        "node_id": "U_kgDOBnhkcg",
        "avatar_url": "https://avatars.githubusercontent.com/u/108553330?v=4",
        "gravatar_id": "",
        "url": "https://api.github.com/users/LizardByte-bot",
        "html_url": "https://github.com/LizardByte-bot",
        "followers_url": "https://api.github.com/users/LizardByte-bot/followers",
        "following_url": "https://api.github.com/users/LizardByte-bot/following{/other_user}",
        "gists_url": "https://api.github.com/users/LizardByte-bot/gists{/gist_id}",
        "starred_url": "https://api.github.com/users/LizardByte-bot/starred{/owner}{/repo}",
        "subscriptions_url": "https://api.github.com/users/LizardByte-bot/subscriptions",
        "organizations_url": "https://api.github.com/users/LizardByte-bot/orgs",
        "repos_url": "https://api.github.com/users/LizardByte-bot/repos",
        "events_url": "https://api.github.com/users/LizardByte-bot/events{/privacy}",
        "received_events_url": "https://api.github.com/users/LizardByte-bot/received_events",
        "type": "User",
        "site_admin": false
      },
      "content_type": "raw",
      "state": "uploaded",
      "size": 596417132,
      "download_count": 163,
      "created_at": "2023-01-09T02:20:23Z",
      "updated_at": "2023-01-09T02:20:42Z",
      "browser_download_url": "https://github.com/LizardByte/Sunshine/releases/download/v0.17.0/sunshine.dmg"
    },
    {
      "url": "https://api.github.com/repos/LizardByte/Sunshine/releases/assets/90983382",
      "id": 90983382,
      "node_id": "RA_kwDOGiedss4FbEvW",
      "name": "sunshine.pkg",
      "label": "",
      "uploader": {
        "login": "LizardByte-bot",
        "id": 108553330,
        "node_id": "U_kgDOBnhkcg",
        "avatar_url": "https://avatars.githubusercontent.com/u/108553330?v=4",
        "gravatar_id": "",
        "url": "https://api.github.com/users/LizardByte-bot",
        "html_url": "https://github.com/LizardByte-bot",
        "followers_url": "https://api.github.com/users/LizardByte-bot/followers",
        "following_url": "https://api.github.com/users/LizardByte-bot/following{/other_user}",
        "gists_url": "https://api.github.com/users/LizardByte-bot/gists{/gist_id}",
        "starred_url": "https://api.github.com/users/LizardByte-bot/starred{/owner}{/repo}",
        "subscriptions_url": "https://api.github.com/users/LizardByte-bot/subscriptions",
        "organizations_url": "https://api.github.com/users/LizardByte-bot/orgs",
        "repos_url": "https://api.github.com/users/LizardByte-bot/repos",
        "events_url": "https://api.github.com/users/LizardByte-bot/events{/privacy}",
        "received_events_url": "https://api.github.com/users/LizardByte-bot/received_events",
        "type": "User",
        "site_admin": false
      },
      "content_type": "raw",
      "state": "uploaded",
      "size": 14593175,
      "download_count": 108,
      "created_at": "2023-01-09T02:20:43Z",
      "updated_at": "2023-01-09T02:20:44Z",
      "browser_download_url": "https://github.com/LizardByte/Sunshine/releases/download/v0.17.0/sunshine.pkg"
    },
    {
      "url": "https://api.github.com/repos/LizardByte/Sunshine/releases/assets/90982867",
      "id": 90982867,
      "node_id": "RA_kwDOGiedss4FbEnT",
      "name": "sunshine.rpm",
      "label": "",
      "uploader": {
        "login": "LizardByte-bot",
        "id": 108553330,
        "node_id": "U_kgDOBnhkcg",
        "avatar_url": "https://avatars.githubusercontent.com/u/108553330?v=4",
        "gravatar_id": "",
        "url": "https://api.github.com/users/LizardByte-bot",
        "html_url": "https://github.com/LizardByte-bot",
        "followers_url": "https://api.github.com/users/LizardByte-bot/followers",
        "following_url": "https://api.github.com/users/LizardByte-bot/following{/other_user}",
        "gists_url": "https://api.github.com/users/LizardByte-bot/gists{/gist_id}",
        "starred_url": "https://api.github.com/users/LizardByte-bot/starred{/owner}{/repo}",
        "subscriptions_url": "https://api.github.com/users/LizardByte-bot/subscriptions",
        "organizations_url": "https://api.github.com/users/LizardByte-bot/orgs",
        "repos_url": "https://api.github.com/users/LizardByte-bot/repos",
        "events_url": "https://api.github.com/users/LizardByte-bot/events{/privacy}",
        "received_events_url": "https://api.github.com/users/LizardByte-bot/received_events",
        "type": "User",
        "site_admin": false
      },
      "content_type": "raw",
      "state": "uploaded",
      "size": 15328923,
      "download_count": 214,
      "created_at": "2023-01-09T02:11:53Z",
      "updated_at": "2023-01-09T02:11:55Z",
      "browser_download_url": "https://github.com/LizardByte/Sunshine/releases/download/v0.17.0/sunshine.rpm"
    },
    {
      "url": "https://api.github.com/repos/LizardByte/Sunshine/releases/assets/90990197",
      "id": 90990197,
      "node_id": "RA_kwDOGiedss4FbGZ1",
      "name": "sunshine_aarch64.flatpak",
      "label": "",
      "uploader": {
        "login": "LizardByte-bot",
        "id": 108553330,
        "node_id": "U_kgDOBnhkcg",
        "avatar_url": "https://avatars.githubusercontent.com/u/108553330?v=4",
        "gravatar_id": "",
        "url": "https://api.github.com/users/LizardByte-bot",
        "html_url": "https://github.com/LizardByte-bot",
        "followers_url": "https://api.github.com/users/LizardByte-bot/followers",
        "following_url": "https://api.github.com/users/LizardByte-bot/following{/other_user}",
        "gists_url": "https://api.github.com/users/LizardByte-bot/gists{/gist_id}",
        "starred_url": "https://api.github.com/users/LizardByte-bot/starred{/owner}{/repo}",
        "subscriptions_url": "https://api.github.com/users/LizardByte-bot/subscriptions",
        "organizations_url": "https://api.github.com/users/LizardByte-bot/orgs",
        "repos_url": "https://api.github.com/users/LizardByte-bot/repos",
        "events_url": "https://api.github.com/users/LizardByte-bot/events{/privacy}",
        "received_events_url": "https://api.github.com/users/LizardByte-bot/received_events",
        "type": "User",
        "site_admin": false
      },
      "content_type": "raw",
      "state": "uploaded",
      "size": 7876096,
      "download_count": 149,
      "created_at": "2023-01-09T04:01:39Z",
      "updated_at": "2023-01-09T04:01:40Z",
      "browser_download_url": "https://github.com/LizardByte/Sunshine/releases/download/v0.17.0/sunshine_aarch64.flatpak"
    },
    {
      "url": "https://api.github.com/repos/LizardByte/Sunshine/releases/assets/90990198",
      "id": 90990198,
      "node_id": "RA_kwDOGiedss4FbGZ2",
      "name": "sunshine_debug_aarch64.flatpak",
      "label": "",
      "uploader": {
        "login": "LizardByte-bot",
        "id": 108553330,
        "node_id": "U_kgDOBnhkcg",
        "avatar_url": "https://avatars.githubusercontent.com/u/108553330?v=4",
        "gravatar_id": "",
        "url": "https://api.github.com/users/LizardByte-bot",
        "html_url": "https://github.com/LizardByte-bot",
        "followers_url": "https://api.github.com/users/LizardByte-bot/followers",
        "following_url": "https://api.github.com/users/LizardByte-bot/following{/other_user}",
        "gists_url": "https://api.github.com/users/LizardByte-bot/gists{/gist_id}",
        "starred_url": "https://api.github.com/users/LizardByte-bot/starred{/owner}{/repo}",
        "subscriptions_url": "https://api.github.com/users/LizardByte-bot/subscriptions",
        "organizations_url": "https://api.github.com/users/LizardByte-bot/orgs",
        "repos_url": "https://api.github.com/users/LizardByte-bot/repos",
        "events_url": "https://api.github.com/users/LizardByte-bot/events{/privacy}",
        "received_events_url": "https://api.github.com/users/LizardByte-bot/received_events",
        "type": "User",
        "site_admin": false
      },
      "content_type": "raw",
      "state": "uploaded",
      "size": 44379456,
      "download_count": 10,
      "created_at": "2023-01-09T04:01:40Z",
      "updated_at": "2023-01-09T04:01:42Z",
      "browser_download_url": "https://github.com/LizardByte/Sunshine/releases/download/v0.17.0/sunshine_debug_aarch64.flatpak"
    },
    {
      "url": "https://api.github.com/repos/LizardByte/Sunshine/releases/assets/90983936",
      "id": 90983936,
      "node_id": "RA_kwDOGiedss4FbE4A",
      "name": "sunshine_debug_x86_64.flatpak",
      "label": "",
      "uploader": {
        "login": "LizardByte-bot",
        "id": 108553330,
        "node_id": "U_kgDOBnhkcg",
        "avatar_url": "https://avatars.githubusercontent.com/u/108553330?v=4",
        "gravatar_id": "",
        "url": "https://api.github.com/users/LizardByte-bot",
        "html_url": "https://github.com/LizardByte-bot",
        "followers_url": "https://api.github.com/users/LizardByte-bot/followers",
        "following_url": "https://api.github.com/users/LizardByte-bot/following{/other_user}",
        "gists_url": "https://api.github.com/users/LizardByte-bot/gists{/gist_id}",
        "starred_url": "https://api.github.com/users/LizardByte-bot/starred{/owner}{/repo}",
        "subscriptions_url": "https://api.github.com/users/LizardByte-bot/subscriptions",
        "organizations_url": "https://api.github.com/users/LizardByte-bot/orgs",
        "repos_url": "https://api.github.com/users/LizardByte-bot/repos",
        "events_url": "https://api.github.com/users/LizardByte-bot/events{/privacy}",
        "received_events_url": "https://api.github.com/users/LizardByte-bot/received_events",
        "type": "User",
        "site_admin": false
      },
      "content_type": "raw",
      "state": "uploaded",
      "size": 45669816,
      "download_count": 41,
      "created_at": "2023-01-09T02:28:43Z",
      "updated_at": "2023-01-09T02:28:45Z",
      "browser_download_url": "https://github.com/LizardByte/Sunshine/releases/download/v0.17.0/sunshine_debug_x86_64.flatpak"
    },
    {
      "url": "https://api.github.com/repos/LizardByte/Sunshine/releases/assets/90983939",
      "id": 90983939,
      "node_id": "RA_kwDOGiedss4FbE4D",
      "name": "sunshine_x86_64.flatpak",
      "label": "",
      "uploader": {
        "login": "LizardByte-bot",
        "id": 108553330,
        "node_id": "U_kgDOBnhkcg",
        "avatar_url": "https://avatars.githubusercontent.com/u/108553330?v=4",
        "gravatar_id": "",
        "url": "https://api.github.com/users/LizardByte-bot",
        "html_url": "https://github.com/LizardByte-bot",
        "followers_url": "https://api.github.com/users/LizardByte-bot/followers",
        "following_url": "https://api.github.com/users/LizardByte-bot/following{/other_user}",
        "gists_url": "https://api.github.com/users/LizardByte-bot/gists{/gist_id}",
        "starred_url": "https://api.github.com/users/LizardByte-bot/starred{/owner}{/repo}",
        "subscriptions_url": "https://api.github.com/users/LizardByte-bot/subscriptions",
        "organizations_url": "https://api.github.com/users/LizardByte-bot/orgs",
        "repos_url": "https://api.github.com/users/LizardByte-bot/repos",
        "events_url": "https://api.github.com/users/LizardByte-bot/events{/privacy}",
        "received_events_url": "https://api.github.com/users/LizardByte-bot/received_events",
        "type": "User",
        "site_admin": false
      },
      "content_type": "raw",
      "state": "uploaded",
      "size": 9952768,
      "download_count": 386,
      "created_at": "2023-01-09T02:28:45Z",
      "updated_at": "2023-01-09T02:28:46Z",
      "browser_download_url": "https://github.com/LizardByte/Sunshine/releases/download/v0.17.0/sunshine_x86_64.flatpak"
    }
  ],
  "tarball_url": "https://api.github.com/repos/LizardByte/Sunshine/tarball/v0.17.0",
  "zipball_url": "https://api.github.com/repos/LizardByte/Sunshine/zipball/v0.17.0",
  "body": "If you are running Sunshine as a service on Windows, we are strongly urging you to update to v0.17.0 as soon as\npossible. Older Windows versions of Sunshine had a security flaw in which the binary was located in a user-writable\nlocation which is problematic when running as a service or on a multi-user system. Additionally, when running Sunshine\nas a service, games and applications were launched as SYSTEM. This could lead to issues with save files and other game\nsettings. In v0.17.0, games now run under your user account without elevated privileges.\n\n### Breaking\n- (Apps) Removed automatic desktop entry (Re-add by adding an empty application named \"Desktop\" with no commands, \"desktop.png\" can be added as the image.)\n- (Windows) Improved user upgrade experience (Suggest to manually uninstall existing Sunshine version before this upgrade. Do NOT select to remove everything, if prompted. Make a backup of config files before uninstall.)\n- (Windows) Move config files to specific directory (files will be migrated automatically if using Windows installer)\n- (Dependencies) Fix npm path (breaking change for package maintainers)\n### Added\n- (macOS) Added initial support for arm64 on macOS through Macports portfile\n- (Input) Added support for foreign keyboard input\n- (Misc) Logs inside the WebUI and log to file\n- (UI/Windows) Added an Apply button to configuration page when running as a service\n- (Input/Windows) Enable Mouse Keys while streaming for systems with no physical mouse\n### Fixed\n- (Video) Improved capture performance\n- (Audio) Improved audio bitrate and quality handling\n- (Apps/Windows) Fixed PATH environment variable handling\n- (Apps/Windows) Use the proper environment variable for the Program Files (x86) folder\n- (Service/Windows) Fix SunshineSvc hanging if an error occurs during startup\n- (Service/Windows) Spawn Sunshine.exe in a job object, so it is terminated if SunshineSvc.exe dies\n- (Video) windows/vram: fix fringing in NV12 colour conversion\n- (Apps/Windows) Launch games under the correct user account\n- (Video) nvenc, amdvce: rework all user presets/options\n- (Network) Generate certificates with unique serial numbers\n- (Service/Windows) Graceful termination on shutdown, logoff, and service stop\n- (Apps/Windows) Fix launching apps when Sunshine is running as admin\n- (Misc) Remove/fix calls to std::abort()\n- (Misc) Remove prompt to press enter after Sunshine exits\n- (Misc) Make log priority consistent for execution messages\n- (Apps) Applications in Moonlight clients are now updated automatically after editing\n- (Video/Linux) Fix wayland capture on nvidia\n- (Audio) Fix 7.1 surround channel mapping\n- (Video) Fix NVENC profile values not applying\n- (Network) Fix origin_web_ui_allowed binding\n- (Service/Windows) Self terminate/restart service if process hangs for 10 seconds\n- (Input/Windows) Fix Windows masked cursor blending with GPU encoders\n- (Video) Color conversion fixes and BT.2020 support\n### Dependencies\n- Bump ffmpeg from 4.4 to 5.1\n- ffmpeg_patches: add amfenc delay/buffering fix\n- CBS moved to ffmpeg submodules\n- Migrate to upstream Simple-Web-Server submodule\n- Bump third-party/TPCircularBuffer from `bce9170` to `8833b3a`\n- Bump third-party/moonlight-common-c from `8169a31` to `ef9ad52`\n- Bump third-party/miniupnp from `6f848ae` to `207cf44`\n- Bump third-party/ViGEmClient from `f719a1d` to `9e842ba`\n- Bump bootstrap from 5.0.0 to 5.2.3\n- Bump @fortawesome/fontawesome-free from 6.2.0 to 6.2.1",
  "discussion_url": "https://github.com/LizardByte/Sunshine/discussions/735",
  "reactions": {
    "url": "https://api.github.com/repos/LizardByte/Sunshine/releases/88260187/reactions",
    "total_count": 37,
    "+1": 0,
    "-1": 0,
    "laugh": 9,
    "hooray": 16,
    "confused": 0,
    "heart": 12,
    "rocket": 0,
    "eyes": 0
  }
}
