{
  "url": "https://api.github.com/repos/bvaisvil/zenith/releases/64564074",
  "assets_url": "https://api.github.com/repos/bvaisvil/zenith/releases/64564074/assets",
  "upload_url": "https://uploads.github.com/repos/bvaisvil/zenith/releases/64564074/assets{?name,label}",
  "html_url": "https://github.com/bvaisvil/zenith/releases/tag/0.13.1",
  "id": 64564074,
  "author": {
    "login": "bvaisvil",
    "id": 3818351,
    "node_id": "MDQ6VXNlcjM4MTgzNTE=",
    "avatar_url": "https://avatars.githubusercontent.com/u/3818351?v=4",
    "gravatar_id": "",
    "url": "https://api.github.com/users/bvaisvil",
    "html_url": "https://github.com/bvaisvil",
    "followers_url": "https://api.github.com/users/bvaisvil/followers",
    "following_url": "https://api.github.com/users/bvaisvil/following{/other_user}",
    "gists_url": "https://api.github.com/users/bvaisvil/gists{/gist_id}",
    "starred_url": "https://api.github.com/users/bvaisvil/starred{/owner}{/repo}",
    "subscriptions_url": "https://api.github.com/users/bvaisvil/subscriptions",
    "organizations_url": "https://api.github.com/users/bvaisvil/orgs",
    "repos_url": "https://api.github.com/users/bvaisvil/repos",
    "events_url": "https://api.github.com/users/bvaisvil/events{/privacy}",
    "received_events_url": "https://api.github.com/users/bvaisvil/received_events",
    "type": "User",
    "site_admin": false
  },
  "node_id": "RE_kwDODHA2vc4D2Stq",
  "tag_name": "0.13.1",
  "target_commitish": "3f64240610fe9c6965da1239a2b7617ef1d1d6e8",
  "name": "0.13.1",
  "draft": false,
  "prerelease": false,
  "created_at": "2022-03-17T19:58:50Z",
  "published_at": "2022-04-15T21:07:33Z",
  "assets": [
    {
      "url": "https://api.github.com/repos/bvaisvil/zenith/releases/assets/62705575",
      "id": 62705575,
      "node_id": "RA_kwDODHA2vc4DvM-n",
      "name": "zenith.x86_64-apple-darwin.tgz",
      "label": null,
      "uploader": {
        "login": "bvaisvil",
        "id": 3818351,
        "node_id": "MDQ6VXNlcjM4MTgzNTE=",
        "avatar_url": "https://avatars.githubusercontent.com/u/3818351?v=4",
        "gravatar_id": "",
        "url": "https://api.github.com/users/bvaisvil",
        "html_url": "https://github.com/bvaisvil",
        "followers_url": "https://api.github.com/users/bvaisvil/followers",
        "following_url": "https://api.github.com/users/bvaisvil/following{/other_user}",
        "gists_url": "https://api.github.com/users/bvaisvil/gists{/gist_id}",
        "starred_url": "https://api.github.com/users/bvaisvil/starred{/owner}{/repo}",
        "subscriptions_url": "https://api.github.com/users/bvaisvil/subscriptions",
        "organizations_url": "https://api.github.com/users/bvaisvil/orgs",
        "repos_url": "https://api.github.com/users/bvaisvil/repos",
        "events_url": "https://api.github.com/users/bvaisvil/events{/privacy}",
        "received_events_url": "https://api.github.com/users/bvaisvil/received_events",
        "type": "User",
        "site_admin": false
      },
      "content_type": "application/gzip",
      "state": "uploaded",
      "size": 722593,
      "download_count": 45,
      "created_at": "2022-04-15T21:03:13Z",
      "updated_at": "2022-04-15T21:03:14Z",
      "browser_download_url": "https://github.com/bvaisvil/zenith/releases/download/0.13.1/zenith.x86_64-apple-darwin.tgz"
    },
    {
      "url": "https://api.github.com/repos/bvaisvil/zenith/releases/assets/62705576",
      "id": 62705576,
      "node_id": "RA_kwDODHA2vc4DvM-o",
      "name": "zenith.x86_64-apple-darwin.tgz.sha256",
      "label": null,
      "uploader": {
        "login": "bvaisvil",
        "id": 3818351,
        "node_id": "MDQ6VXNlcjM4MTgzNTE=",
        "avatar_url": "https://avatars.githubusercontent.com/u/3818351?v=4",
        "gravatar_id": "",
        "url": "https://api.github.com/users/bvaisvil",
        "html_url": "https://github.com/bvaisvil",
        "followers_url": "https://api.github.com/users/bvaisvil/followers",
        "following_url": "https://api.github.com/users/bvaisvil/following{/other_user}",
        "gists_url": "https://api.github.com/users/bvaisvil/gists{/gist_id}",
        "starred_url": "https://api.github.com/users/bvaisvil/starred{/owner}{/repo}",
        "subscriptions_url": "https://api.github.com/users/bvaisvil/subscriptions",
        "organizations_url": "https://api.github.com/users/bvaisvil/orgs",
        "repos_url": "https://api.github.com/users/bvaisvil/repos",
        "events_url": "https://api.github.com/users/bvaisvil/events{/privacy}",
        "received_events_url": "https://api.github.com/users/bvaisvil/received_events",
        "type": "User",
        "site_admin": false
      },
      "content_type": "application/octet-stream",
      "state": "uploaded",
      "size": 97,
      "download_count": 8,
      "created_at": "2022-04-15T21:03:14Z",
      "updated_at": "2022-04-15T21:03:14Z",
      "browser_download_url": "https://github.com/bvaisvil/zenith/releases/download/0.13.1/zenith.x86_64-apple-darwin.tgz.sha256"
    },
    {
      "url": "https://api.github.com/repos/bvaisvil/zenith/releases/assets/62705577",
      "id": 62705577,
      "node_id": "RA_kwDODHA2vc4DvM-p",
      "name": "zenith.x86_64-unknown-linux-musl.tgz",
      "label": null,
      "uploader": {
        "login": "bvaisvil",
        "id": 3818351,
        "node_id": "MDQ6VXNlcjM4MTgzNTE=",
        "avatar_url": "https://avatars.githubusercontent.com/u/3818351?v=4",
        "gravatar_id": "",
        "url": "https://api.github.com/users/bvaisvil",
        "html_url": "https://github.com/bvaisvil",
        "followers_url": "https://api.github.com/users/bvaisvil/followers",
        "following_url": "https://api.github.com/users/bvaisvil/following{/other_user}",
        "gists_url": "https://api.github.com/users/bvaisvil/gists{/gist_id}",
        "starred_url": "https://api.github.com/users/bvaisvil/starred{/owner}{/repo}",
        "subscriptions_url": "https://api.github.com/users/bvaisvil/subscriptions",
        "organizations_url": "https://api.github.com/users/bvaisvil/orgs",
        "repos_url": "https://api.github.com/users/bvaisvil/repos",
        "events_url": "https://api.github.com/users/bvaisvil/events{/privacy}",
        "received_events_url": "https://api.github.com/users/bvaisvil/received_events",
        "type": "User",
        "site_admin": false
      },
      "content_type": "application/gzip",
      "state": "uploaded",
      "size": 791498,
      "download_count": 442,
      "created_at": "2022-04-15T21:03:14Z",
      "updated_at": "2022-04-15T21:03:15Z",
      "browser_download_url": "https://github.com/bvaisvil/zenith/releases/download/0.13.1/zenith.x86_64-unknown-linux-musl.tgz"
    },
    {
      "url": "https://api.github.com/repos/bvaisvil/zenith/releases/assets/62705578",
      "id": 62705578,
      "node_id": "RA_kwDODHA2vc4DvM-q",
      "name": "zenith.x86_64-unknown-linux-musl.tgz.sha256",
      "label": null,
      "uploader": {
        "login": "bvaisvil",
        "id": 3818351,
        "node_id": "MDQ6VXNlcjM4MTgzNTE=",
        "avatar_url": "https://avatars.githubusercontent.com/u/3818351?v=4",
        "gravatar_id": "",
        "url": "https://api.github.com/users/bvaisvil",
        "html_url": "https://github.com/bvaisvil",
        "followers_url": "https://api.github.com/users/bvaisvil/followers",
        "following_url": "https://api.github.com/users/bvaisvil/following{/other_user}",
        "gists_url": "https://api.github.com/users/bvaisvil/gists{/gist_id}",
        "starred_url": "https://api.github.com/users/bvaisvil/starred{/owner}{/repo}",
        "subscriptions_url": "https://api.github.com/users/bvaisvil/subscriptions",
        "organizations_url": "https://api.github.com/users/bvaisvil/orgs",
        "repos_url": "https://api.github.com/users/bvaisvil/repos",
        "events_url": "https://api.github.com/users/bvaisvil/events{/privacy}",
        "received_events_url": "https://api.github.com/users/bvaisvil/received_events",
        "type": "User",
        "site_admin": false
      },
      "content_type": "application/octet-stream",
      "state": "uploaded",
      "size": 103,
      "download_count": 116,
      "created_at": "2022-04-15T21:03:15Z",
      "updated_at": "2022-04-15T21:03:15Z",
      "browser_download_url": "https://github.com/bvaisvil/zenith/releases/download/0.13.1/zenith.x86_64-unknown-linux-musl.tgz.sha256"
    },
    {
      "url": "https://api.github.com/repos/bvaisvil/zenith/releases/assets/62705573",
      "id": 62705573,
      "node_id": "RA_kwDODHA2vc4DvM-l",
      "name": "zenith_0.13.0-1_amd64.deb",
      "label": null,
      "uploader": {
        "login": "bvaisvil",
        "id": 3818351,
        "node_id": "MDQ6VXNlcjM4MTgzNTE=",
        "avatar_url": "https://avatars.githubusercontent.com/u/3818351?v=4",
        "gravatar_id": "",
        "url": "https://api.github.com/users/bvaisvil",
        "html_url": "https://github.com/bvaisvil",
        "followers_url": "https://api.github.com/users/bvaisvil/followers",
        "following_url": "https://api.github.com/users/bvaisvil/following{/other_user}",
        "gists_url": "https://api.github.com/users/bvaisvil/gists{/gist_id}",
        "starred_url": "https://api.github.com/users/bvaisvil/starred{/owner}{/repo}",
        "subscriptions_url": "https://api.github.com/users/bvaisvil/subscriptions",
        "organizations_url": "https://api.github.com/users/bvaisvil/orgs",
        "repos_url": "https://api.github.com/users/bvaisvil/repos",
        "events_url": "https://api.github.com/users/bvaisvil/events{/privacy}",
        "received_events_url": "https://api.github.com/users/bvaisvil/received_events",
        "type": "User",
        "site_admin": false
      },
      "content_type": "application/x-deb",
      "state": "uploaded",
      "size": 728584,
      "download_count": 1278,
      "created_at": "2022-04-15T21:03:12Z",
      "updated_at": "2022-04-15T21:03:13Z",
      "browser_download_url": "https://github.com/bvaisvil/zenith/releases/download/0.13.1/zenith_0.13.0-1_amd64.deb"
    },
    {
      "url": "https://api.github.com/repos/bvaisvil/zenith/releases/assets/62705574",
      "id": 62705574,
      "node_id": "RA_kwDODHA2vc4DvM-m",
      "name": "zenith_0.13.0-1_amd64.deb.sha256",
      "label": null,
      "uploader": {
        "login": "bvaisvil",
        "id": 3818351,
        "node_id": "MDQ6VXNlcjM4MTgzNTE=",
        "avatar_url": "https://avatars.githubusercontent.com/u/3818351?v=4",
        "gravatar_id": "",
        "url": "https://api.github.com/users/bvaisvil",
        "html_url": "https://github.com/bvaisvil",
        "followers_url": "https://api.github.com/users/bvaisvil/followers",
        "following_url": "https://api.github.com/users/bvaisvil/following{/other_user}",
        "gists_url": "https://api.github.com/users/bvaisvil/gists{/gist_id}",
        "starred_url": "https://api.github.com/users/bvaisvil/starred{/owner}{/repo}",
        "subscriptions_url": "https://api.github.com/users/bvaisvil/subscriptions",
        "organizations_url": "https://api.github.com/users/bvaisvil/orgs",
        "repos_url": "https://api.github.com/users/bvaisvil/repos",
        "events_url": "https://api.github.com/users/bvaisvil/events{/privacy}",
        "received_events_url": "https://api.github.com/users/bvaisvil/received_events",
        "type": "User",
        "site_admin": false
      },
      "content_type": "application/octet-stream",
      "state": "uploaded",
      "size": 92,
      "download_count": 20,
      "created_at": "2022-04-15T21:03:13Z",
      "updated_at": "2022-04-15T21:03:13Z",
      "browser_download_url": "https://github.com/bvaisvil/zenith/releases/download/0.13.1/zenith_0.13.0-1_amd64.deb.sha256"
    }
  ],
  "tarball_url": "https://api.github.com/repos/bvaisvil/zenith/tarball/0.13.1",
  "zipball_url": "https://api.github.com/repos/bvaisvil/zenith/zipball/0.13.1",
  "body": "- bfdcf17b9f20177fd03eb5f9d44db40778a31806 Fix for Issue #96 (thanks @murlakatamenka)",
  "reactions": {
    "url": "https://api.github.com/repos/bvaisvil/zenith/releases/64564074/reactions",
    "total_count": 1,
    "+1": 0,
    "-1": 0,
    "laugh": 0,
    "hooray": 0,
    "confused": 0,
    "heart": 1,
    "rocket": 0,
    "eyes": 0
  },
  "mentions_count": 1
}
